{
  "date": "2026-06-20",
  "fixtures": [
    {
      "id": 1261,
      "date": "2026-06-20T20:50:00.000Z",
      "roundId": 1,
      "player1Id": 26421,
      "player2Id": 39310,
      "tournamentId": 21336,
      "timeGame": null,
      "seed1": "q",
      "seed2": null,
      "live": null,
      "player1": {
        "id": 26421,
        "name": "Jan Choinski",
        "countryAcr": "GBR"
      },
      "player2": {
        "id": 39310,
        "name": "Yibing Wu",
        "countryAcr": "CHN"
      },
      "tournament": {
        "id": 21336,
        "name": "Lexus Eastbourne Open - Eastbourne",
        "courtId": 5,
        "date": "2026-06-22T00:00:00.000Z",
        "rankId": 2,
        "countryAcr": "GBR",
        "court": {
          "id": 5,
          "name": "Grass"
        },
        "rank": {
          "id": 2,
          "name": "Main tour"
        },
        "country": null
      },
      "round": {
        "id": 1,
        "name": "Q1"
      }
    },
    {
      "id": 1258,
      "date": "2026-06-20T20:05:00.000Z",
      "roundId": 1,
      "player1Id": 18736,
      "player2Id": 39438,
      "tournamentId": 21336,
      "timeGame": null,
      "seed1": null,
      "seed2": null,
      "live": null,
      "player1": {
        "id": 18736,
        "name": "Marcos Giron",
        "countryAcr": "USA"
      },
      "player2": {
        "id": 39438,
        "name": "Charles Broom",
        "countryAcr": "GBR"
      },
      "tournament": {
        "id": 21336,
        "name": "Lexus Eastbourne Open - Eastbourne",
        "courtId": 5,
        "date": "2026-06-22T00:00:00.000Z",
        "rankId": 2,
        "countryAcr": "GBR",
        "court": {
          "id": 5,
          "name": "Grass"
        },
        "rank": {
          "id": 2,
          "name": "Main tour"
        },
        "country": null
      },
      "round": {
        "id": 1,
        "name": "Q1"
      }
    },
    {
      "id": 1278,
      "date": "2026-06-20T18:35:00.000Z",
      "roundId": 1,
      "player1Id": 71188,
      "player2Id": 11517,
      "tournamentId": 21336,
      "timeGame": null,
      "seed1": "q",
      "seed2": null,
      "live": null,
      "player1": {
        "id": 71188,
        "name": "Giles Hussey",
        "countryAcr": "GBR"
      },
      "player2": {
        "id": 11517,
        "name": "James Duckworth",
        "countryAcr": "AUS"
      },
      "tournament": {
        "id": 21336,
        "name": "Lexus Eastbourne Open - Eastbourne",
        "courtId": 5,
        "date": "2026-06-22T00:00:00.000Z",
        "rankId": 2,
        "countryAcr": "GBR",
        "court": {
          "id": 5,
          "name": "Grass"
        },
        "rank": {
          "id": 2,
          "name": "Main tour"
        },
        "country": null
      },
      "round": {
        "id": 1,
        "name": "Q1"
      }
    },
    {
      "id": 1257,
      "date": "2026-06-20T17:15:00.000Z",
      "roundId": 1,
      "player1Id": 12653,
      "player2Id": 73608,
      "tournamentId": 21336,
      "timeGame": null,
      "seed1": null,
      "seed2": null,
      "live": null,
      "player1": {
        "id": 12653,
        "name": "Marco Trungelliti",
        "countryAcr": "ARG"
      },
      "player2": {
        "id": 73608,
        "name": "Felix Gill",
        "countryAcr": "GBR"
      },
      "tournament": {
        "id": 21336,
        "name": "Lexus Eastbourne Open - Eastbourne",
        "courtId": 5,
        "date": "2026-06-22T00:00:00.000Z",
        "rankId": 2,
        "countryAcr": "GBR",
        "court": {
          "id": 5,
          "name": "Grass"
        },
        "rank": {
          "id": 2,
          "name": "Main tour"
        },
        "country": null
      },
      "round": {
        "id": 1,
        "name": "Q1"
      }
    },
    {
      "id": 1275,
      "date": "2026-06-20T16:45:00.000Z",
      "roundId": 1,
      "player1Id": 59443,
      "player2Id": 56197,
      "tournamentId": 21336,
      "timeGame": null,
      "seed1": null,
      "seed2": null,
      "live": null,
      "player1": {
        "id": 59443,
        "name": "Hamish Stewart",
        "countryAcr": "GBR"
      },
      "player2": {
        "id": 56197,
        "name": "Emilio Nava",
        "countryAcr": "USA"
      },
      "tournament": {
        "id": 21336,
        "name": "Lexus Eastbourne Open - Eastbourne",
        "courtId": 5,
        "date": "2026-06-22T00:00:00.000Z",
        "rankId": 2,
        "countryAcr": "GBR",
        "court": {
          "id": 5,
          "name": "Grass"
        },
        "rank": {
          "id": 2,
          "name": "Main tour"
        },
        "country": null
      },
      "round": {
        "id": 1,
        "name": "Q1"
      }
    },
    {
      "id": 1232,
      "date": "2026-06-20T16:05:00.000Z",
      "roundId": 1,
      "player1Id": 73620,
      "player2Id": 35297,
      "tournamentId": 21335,
      "timeGame": null,
      "seed1": null,
      "seed2": null,
      "live": null,
      "player1": {
        "id": 73620,
        "name": "Zachary Svajda",
        "countryAcr": "USA"
      },
      "player2": {
        "id": 35297,
        "name": "Marc-Andrea Huesler",
        "countryAcr": "SUI"
      },
      "tournament": {
        "id": 21335,
        "name": "Mallorca Championships - Mallorca",
        "courtId": 5,
        "date": "2026-06-22T00:00:00.000Z",
        "rankId": 2,
        "countryAcr": "ESP",
        "court": {
          "id": 5,
          "name": "Grass"
        },
        "rank": {
          "id": 2,
          "name": "Main tour"
        },
        "country": null
      },
      "round": {
        "id": 1,
        "name": "Q1"
      }
    },
    {
      "id": 1209,
      "date": "2026-06-20T15:25:00.000Z",
      "roundId": 1,
      "player1Id": 13447,
      "player2Id": 9043,
      "tournamentId": 21335,
      "timeGame": null,
      "seed1": "q",
      "seed2": null,
      "live": null,
      "player1": {
        "id": 13447,
        "name": "Damir Dzumhur",
        "countryAcr": "BIH"
      },
      "player2": {
        "id": 9043,
        "name": "Mikhail Kukushkin",
        "countryAcr": "KAZ"
      },
      "tournament": {
        "id": 21335,
        "name": "Mallorca Championships - Mallorca",
        "courtId": 5,
        "date": "2026-06-22T00:00:00.000Z",
        "rankId": 2,
        "countryAcr": "ESP",
        "court": {
          "id": 5,
          "name": "Grass"
        },
        "rank": {
          "id": 2,
          "name": "Main tour"
        },
        "country": null
      },
      "round": {
        "id": 1,
        "name": "Q1"
      }
    },
    {
      "id": 1263,
      "date": "2026-06-20T15:25:00.000Z",
      "roundId": 1,
      "player1Id": 28267,
      "player2Id": 65558,
      "tournamentId": 21336,
      "timeGame": null,
      "seed1": "q",
      "seed2": null,
      "live": null,
      "player1": {
        "id": 28267,
        "name": "Aleksandar Vukic",
        "countryAcr": "AUS"
      },
      "player2": {
        "id": 65558,
        "name": "Harry Wendelken",
        "countryAcr": "GBR"
      },
      "tournament": {
        "id": 21336,
        "name": "Lexus Eastbourne Open - Eastbourne",
        "courtId": 5,
        "date": "2026-06-22T00:00:00.000Z",
        "rankId": 2,
        "countryAcr": "GBR",
        "court": {
          "id": 5,
          "name": "Grass"
        },
        "rank": {
          "id": 2,
          "name": "Main tour"
        },
        "country": null
      },
      "round": {
        "id": 1,
        "name": "Q1"
      }
    },
    {
      "id": 1230,
      "date": "2026-06-20T13:35:00.000Z",
      "roundId": 1,
      "player1Id": 47752,
      "player2Id": 92247,
      "tournamentId": 21335,
      "timeGame": null,
      "seed1": "q",
      "seed2": null,
      "live": null,
      "player1": {
        "id": 47752,
        "name": "Adam Walton",
        "countryAcr": "AUS"
      },
      "player2": {
        "id": 92247,
        "name": "Federico Bondioli",
        "countryAcr": "ITA"
      },
      "tournament": {
        "id": 21335,
        "name": "Mallorca Championships - Mallorca",
        "courtId": 5,
        "date": "2026-06-22T00:00:00.000Z",
        "rankId": 2,
        "countryAcr": "ESP",
        "court": {
          "id": 5,
          "name": "Grass"
        },
        "rank": {
          "id": 2,
          "name": "Main tour"
        },
        "country": null
      },
      "round": {
        "id": 1,
        "name": "Q1"
      }
    },
    {
      "id": 1234,
      "date": "2026-06-20T13:30:00.000Z",
      "roundId": 1,
      "player1Id": 76009,
      "player2Id": 64891,
      "tournamentId": 21335,
      "timeGame": null,
      "seed1": null,
      "seed2": null,
      "live": null,
      "player1": {
        "id": 76009,
        "name": "Abedallah Shelbayh",
        "countryAcr": "JOR"
      },
      "player2": {
        "id": 64891,
        "name": "Alexander Shevchenko",
        "countryAcr": "KAZ"
      },
      "tournament": {
        "id": 21335,
        "name": "Mallorca Championships - Mallorca",
        "courtId": 5,
        "date": "2026-06-22T00:00:00.000Z",
        "rankId": 2,
        "countryAcr": "ESP",
        "court": {
          "id": 5,
          "name": "Grass"
        },
        "rank": {
          "id": 2,
          "name": "Main tour"
        },
        "country": null
      },
      "round": {
        "id": 1,
        "name": "Q1"
      }
    },
    {
      "id": 1285,
      "date": "2026-06-20T13:05:00.000Z",
      "roundId": 1,
      "player1Id": 79068,
      "player2Id": 25171,
      "tournamentId": 21336,
      "timeGame": null,
      "seed1": null,
      "seed2": null,
      "live": null,
      "player1": {
        "id": 79068,
        "name": "Toby Samuel",
        "countryAcr": "GBR"
      },
      "player2": {
        "id": 25171,
        "name": "Quentin Halys",
        "countryAcr": "FRA"
      },
      "tournament": {
        "id": 21336,
        "name": "Lexus Eastbourne Open - Eastbourne",
        "courtId": 5,
        "date": "2026-06-22T00:00:00.000Z",
        "rankId": 2,
        "countryAcr": "GBR",
        "court": {
          "id": 5,
          "name": "Grass"
        },
        "rank": {
          "id": 2,
          "name": "Main tour"
        },
        "country": null
      },
      "round": {
        "id": 1,
        "name": "Q1"
      }
    },
    {
      "id": 1280,
      "date": "2026-06-20T13:02:00.000Z",
      "roundId": 1,
      "player1Id": 73956,
      "player2Id": 53159,
      "tournamentId": 21336,
      "timeGame": null,
      "seed1": "q",
      "seed2": null,
      "live": null,
      "player1": {
        "id": 73956,
        "name": "Matteo Arnaldi",
        "countryAcr": "ITA"
      },
      "player2": {
        "id": 53159,
        "name": "Alastair Gray",
        "countryAcr": "GBR"
      },
      "tournament": {
        "id": 21336,
        "name": "Lexus Eastbourne Open - Eastbourne",
        "courtId": 5,
        "date": "2026-06-22T00:00:00.000Z",
        "rankId": 2,
        "countryAcr": "GBR",
        "court": {
          "id": 5,
          "name": "Grass"
        },
        "rank": {
          "id": 2,
          "name": "Main tour"
        },
        "country": null
      },
      "round": {
        "id": 1,
        "name": "Q1"
      }
    },
    {
      "id": 1226,
      "date": "2026-06-20T12:05:00.000Z",
      "roundId": 1,
      "player1Id": 34539,
      "player2Id": 111613,
      "tournamentId": 21335,
      "timeGame": null,
      "seed1": "q",
      "seed2": null,
      "live": null,
      "player1": {
        "id": 34539,
        "name": "Alex Molcan",
        "countryAcr": "SVK"
      },
      "player2": {
        "id": 111613,
        "name": "Ziga Sesko",
        "countryAcr": "SLO"
      },
      "tournament": {
        "id": 21335,
        "name": "Mallorca Championships - Mallorca",
        "courtId": 5,
        "date": "2026-06-22T00:00:00.000Z",
        "rankId": 2,
        "countryAcr": "ESP",
        "court": {
          "id": 5,
          "name": "Grass"
        },
        "rank": {
          "id": 2,
          "name": "Main tour"
        },
        "country": null
      },
      "round": {
        "id": 1,
        "name": "Q1"
      }
    },
    {
      "id": 1237,
      "date": "2026-06-20T12:05:00.000Z",
      "roundId": 1,
      "player1Id": 81980,
      "player2Id": 90774,
      "tournamentId": 21335,
      "timeGame": null,
      "seed1": null,
      "seed2": null,
      "live": null,
      "player1": {
        "id": 81980,
        "name": "Murphy Cassone",
        "countryAcr": "USA"
      },
      "player2": {
        "id": 90774,
        "name": "Filippo Romano",
        "countryAcr": "ITA"
      },
      "tournament": {
        "id": 21335,
        "name": "Mallorca Championships - Mallorca",
        "courtId": 5,
        "date": "2026-06-22T00:00:00.000Z",
        "rankId": 2,
        "countryAcr": "ESP",
        "court": {
          "id": 5,
          "name": "Grass"
        },
        "rank": {
          "id": 2,
          "name": "Main tour"
        },
        "country": null
      },
      "round": {
        "id": 1,
        "name": "Q1"
      }
    },
    {
      "id": 1239,
      "date": "2026-06-20T12:00:00.000Z",
      "roundId": 1,
      "player1Id": 83330,
      "player2Id": 85308,
      "tournamentId": 21335,
      "timeGame": null,
      "seed1": null,
      "seed2": null,
      "live": null,
      "player1": {
        "id": 83330,
        "name": "Antoine Ghibaudo",
        "countryAcr": "FRA"
      },
      "player2": {
        "id": 85308,
        "name": "Petr Bar Biryukov",
        "countryAcr": "RUS"
      },
      "tournament": {
        "id": 21335,
        "name": "Mallorca Championships - Mallorca",
        "courtId": 5,
        "date": "2026-06-22T00:00:00.000Z",
        "rankId": 2,
        "countryAcr": "ESP",
        "court": {
          "id": 5,
          "name": "Grass"
        },
        "rank": {
          "id": 2,
          "name": "Main tour"
        },
        "country": null
      },
      "round": {
        "id": 1,
        "name": "Q1"
      }
    },
    {
      "id": 1613,
      "date": "2026-06-20T22:10:00.000Z",
      "roundId": 10,
      "player1Id": 91485,
      "player2Id": 96788,
      "tournamentId": 21793,
      "timeGame": null,
      "seed1": "WC",
      "seed2": "4",
      "live": null,
      "player1": {
        "id": 91485,
        "name": "Bryce Nakashima",
        "countryAcr": "USA"
      },
      "player2": {
        "id": 96788,
        "name": "Kenta Miyoshi",
        "countryAcr": "JPN"
      },
      "tournament": {
        "id": 21793,
        "name": "M15 Irvine",
        "courtId": 1,
        "date": "2026-06-15T00:00:00.000Z",
        "rankId": 0,
        "countryAcr": "USA",
        "court": {
          "id": 1,
          "name": "Hard"
        },
        "rank": null,
        "country": null
      },
      "round": {
        "id": 10,
        "name": "1/2"
      }
    },
    {
      "id": 1636,
      "date": "2026-06-20T21:15:00.000Z",
      "roundId": 10,
      "player1Id": 111370,
      "player2Id": 29800,
      "tournamentId": 21793,
      "timeGame": null,
      "seed1": null,
      "seed2": "2",
      "live": null,
      "player1": {
        "id": 111370,
        "name": "Spencer Johnson",
        "countryAcr": "USA"
      },
      "player2": {
        "id": 29800,
        "name": "Strong Kirchheimer",
        "countryAcr": "USA"
      },
      "tournament": {
        "id": 21793,
        "name": "M15 Irvine",
        "courtId": 1,
        "date": "2026-06-15T00:00:00.000Z",
        "rankId": 0,
        "countryAcr": "USA",
        "court": {
          "id": 1,
          "name": "Hard"
        },
        "rank": null,
        "country": null
      },
      "round": {
        "id": 10,
        "name": "1/2"
      }
    },
    {
      "id": 1468,
      "date": "2026-06-20T19:05:00.000Z",
      "roundId": 10,
      "player1Id": 46722,
      "player2Id": 79066,
      "tournamentId": 21786,
      "timeGame": null,
      "seed1": "WC",
      "seed2": "1",
      "live": null,
      "player1": {
        "id": 46722,
        "name": "Jeff Wolf",
        "countryAcr": "USA"
      },
      "player2": {
        "id": 79066,
        "name": "Andres Martin",
        "countryAcr": "USA"
      },
      "tournament": {
        "id": 21786,
        "name": "M25 Tulsa",
        "courtId": 1,
        "date": "2026-06-15T00:00:00.000Z",
        "rankId": 0,
        "countryAcr": "USA",
        "court": {
          "id": 1,
          "name": "Hard"
        },
        "rank": null,
        "country": null
      },
      "round": {
        "id": 10,
        "name": "1/2"
      }
    },
    {
      "id": 1501,
      "date": "2026-06-20T19:05:00.000Z",
      "roundId": 10,
      "player1Id": 103365,
      "player2Id": 64915,
      "tournamentId": 21786,
      "timeGame": null,
      "seed1": null,
      "seed2": "5",
      "live": null,
      "player1": {
        "id": 103365,
        "name": "Gavin Young",
        "countryAcr": "USA"
      },
      "player2": {
        "id": 64915,
        "name": "Andrew Fenty",
        "countryAcr": "USA"
      },
      "tournament": {
        "id": 21786,
        "name": "M25 Tulsa",
        "courtId": 1,
        "date": "2026-06-15T00:00:00.000Z",
        "rankId": 0,
        "countryAcr": "USA",
        "court": {
          "id": 1,
          "name": "Hard"
        },
        "rank": null,
        "country": null
      },
      "round": {
        "id": 10,
        "name": "1/2"
      }
    },
    {
      "id": 1538,
      "date": "2026-06-20T13:35:00.000Z",
      "roundId": 10,
      "player1Id": 69536,
      "player2Id": 89678,
      "tournamentId": 21790,
      "timeGame": null,
      "seed1": "4",
      "seed2": null,
      "live": null,
      "player1": {
        "id": 69536,
        "name": "Tiago Torres",
        "countryAcr": "POR"
      },
      "player2": {
        "id": 89678,
        "name": "Pablo Martinez Gomez",
        "countryAcr": "ESP"
      },
      "tournament": {
        "id": 21790,
        "name": "M25 Lourinha",
        "courtId": 1,
        "date": "2026-06-15T00:00:00.000Z",
        "rankId": 0,
        "countryAcr": "POR",
        "court": {
          "id": 1,
          "name": "Hard"
        },
        "rank": null,
        "country": null
      },
      "round": {
        "id": 10,
        "name": "1/2"
      }
    },
    {
      "id": 1676,
      "date": "2026-06-20T12:35:00.000Z",
      "roundId": 10,
      "player1Id": 64238,
      "player2Id": 28774,
      "tournamentId": 21795,
      "timeGame": null,
      "seed1": "2",
      "seed2": "4",
      "live": null,
      "player1": {
        "id": 64238,
        "name": "Pietro Orlando Fellin",
        "countryAcr": "ITA"
      },
      "player2": {
        "id": 28774,
        "name": "Khumoun Sultanov",
        "countryAcr": "UZB"
      },
      "tournament": {
        "id": 21795,
        "name": "M15 Gyula",
        "courtId": 2,
        "date": "2026-06-15T00:00:00.000Z",
        "rankId": 0,
        "countryAcr": "HUN",
        "court": {
          "id": 2,
          "name": "Clay"
        },
        "rank": null,
        "country": null
      },
      "round": {
        "id": 10,
        "name": "1/2"
      }
    },
    {
      "id": 1570,
      "date": "2026-06-20T12:05:00.000Z",
      "roundId": 10,
      "player1Id": 103054,
      "player2Id": 71976,
      "tournamentId": 21790,
      "timeGame": null,
      "seed1": null,
      "seed2": "2",
      "live": null,
      "player1": {
        "id": 103054,
        "name": "Thijs Boogaard",
        "countryAcr": "NED"
      },
      "player2": {
        "id": 71976,
        "name": "Fabrizio Andaloro",
        "countryAcr": "ITA"
      },
      "tournament": {
        "id": 21790,
        "name": "M25 Lourinha",
        "courtId": 1,
        "date": "2026-06-15T00:00:00.000Z",
        "rankId": 0,
        "countryAcr": "POR",
        "court": {
          "id": 1,
          "name": "Hard"
        },
        "rank": null,
        "country": null
      },
      "round": {
        "id": 10,
        "name": "1/2"
      }
    },
    {
      "id": 1706,
      "date": "2026-06-20T11:00:00.000Z",
      "roundId": 10,
      "player1Id": 97066,
      "player2Id": 48023,
      "tournamentId": 21795,
      "timeGame": null,
      "seed1": null,
      "seed2": "7",
      "live": null,
      "player1": {
        "id": 97066,
        "name": "Nico Hipfl",
        "countryAcr": "AUT"
      },
      "player2": {
        "id": 48023,
        "name": "Aleksandr Braynin",
        "countryAcr": "UKR"
      },
      "tournament": {
        "id": 21795,
        "name": "M15 Gyula",
        "courtId": 2,
        "date": "2026-06-15T00:00:00.000Z",
        "rankId": 0,
        "countryAcr": "HUN",
        "court": {
          "id": 2,
          "name": "Clay"
        },
        "rank": null,
        "country": null
      },
      "round": {
        "id": 10,
        "name": "1/2"
      }
    },
    {
      "id": 1616,
      "date": "2026-06-20T04:30:00.000Z",
      "roundId": 9,
      "player1Id": 91485,
      "player2Id": 119381,
      "tournamentId": 21793,
      "timeGame": null,
      "seed1": "WC",
      "seed2": "8",
      "live": null,
      "player1": {
        "id": 91485,
        "name": "Bryce Nakashima",
        "countryAcr": "USA"
      },
      "player2": {
        "id": 119381,
        "name": "Ronit Karki",
        "countryAcr": "USA"
      },
      "tournament": {
        "id": 21793,
        "name": "M15 Irvine",
        "courtId": 1,
        "date": "2026-06-15T00:00:00.000Z",
        "rankId": 0,
        "countryAcr": "USA",
        "court": {
          "id": 1,
          "name": "Hard"
        },
        "rank": null,
        "country": null
      },
      "round": {
        "id": 9,
        "name": "1/4"
      }
    },
    {
      "id": 1629,
      "date": "2026-06-20T01:45:00.000Z",
      "roundId": 9,
      "player1Id": 96788,
      "player2Id": 99918,
      "tournamentId": 21793,
      "timeGame": null,
      "seed1": "4",
      "seed2": null,
      "live": null,
      "player1": {
        "id": 96788,
        "name": "Kenta Miyoshi",
        "countryAcr": "JPN"
      },
      "player2": {
        "id": 99918,
        "name": "Rudy Quan",
        "countryAcr": "USA"
      },
      "tournament": {
        "id": 21793,
        "name": "M15 Irvine",
        "courtId": 1,
        "date": "2026-06-15T00:00:00.000Z",
        "rankId": 0,
        "countryAcr": "USA",
        "court": {
          "id": 1,
          "name": "Hard"
        },
        "rank": null,
        "country": null
      },
      "round": {
        "id": 9,
        "name": "1/4"
      }
    }
  ],
  "count": 25,
  "fetchedAt": 1782079868962
}