{
  "Clay": [
    {
      "id": "860319",
      "date": "2020-09-28",
      "tournamentId": 16801,
      "tournamentName": "Biella Challenger",
      "opponentId": 35296,
      "opponentName": "Remy Bertola",
      "won": false,
      "result": "7-5 7-5"
    },
    {
      "id": "842717",
      "date": "2020-09-23",
      "tournamentId": 16462,
      "tournamentName": "French Open - Paris",
      "opponentId": 9649,
      "opponentName": "Jason Jung",
      "won": false,
      "result": "6-4 6-3"
    },
    {
      "id": "812384",
      "date": "2019-06-28",
      "tournamentId": 15988,
      "tournamentName": "Milan Challenger",
      "opponentId": 18477,
      "opponentName": "Hugo Dellien",
      "won": false,
      "result": "6-2 6-3"
    },
    {
      "id": "812361",
      "date": "2019-06-20",
      "tournamentId": 15987,
      "tournamentName": "Parma Challenger",
      "opponentId": 33904,
      "opponentName": "Raul Brancaccio",
      "won": true,
      "result": "6-2 6-3"
    },
    {
      "id": "757266",
      "date": "2018-08-02",
      "tournamentId": 15217,
      "tournamentName": "Sopot Challenger",
      "opponentId": 18477,
      "opponentName": "Hugo Dellien",
      "won": true,
      "result": "6-2 3-6 6-3"
    },
    {
      "id": "733539",
      "date": "2018-03-09",
      "tournamentId": 14906,
      "tournamentName": "Santiago Challenger",
      "opponentId": 20104,
      "opponentName": "Marco Cecchinato",
      "won": false,
      "result": "4-6 6-1 6-4"
    }
  ],
  "Hard": [
    {
      "id": "921977",
      "date": "2022-03-09",
      "tournamentId": 17677,
      "tournamentName": "Monterrey Challenger",
      "opponentId": 35036,
      "opponentName": "Geoffrey Blancaneaux",
      "won": false,
      "result": "6-3 6-1"
    },
    {
      "id": "921992",
      "date": "2022-03-07",
      "tournamentId": 17677,
      "tournamentName": "Monterrey Challenger",
      "opponentId": 22269,
      "opponentName": "Kaichi Uchida",
      "won": true,
      "result": "6-3 6-3"
    }
  ],
  "Grass": [
    {
      "id": "867708",
      "date": "2021-06-22",
      "tournamentId": 16919,
      "tournamentName": "Wimbledon - London",
      "opponentId": 58327,
      "opponentName": "Tomas Machac",
      "won": false,
      "result": "7-5 4-6 10-8"
    }
  ],
  "updatedAt": 1782339543974,
  "playerName": "Tommy Robredo"
}