{
  "Clay": [
    {
      "id": "1264417",
      "date": "2026-05-26",
      "tournamentId": 21671,
      "tournamentName": "Chisinau Challenger",
      "opponentId": 48825,
      "opponentName": "Daniil Glinka",
      "won": false,
      "result": "6-3 6-3"
    },
    {
      "id": "1264411",
      "date": "2026-05-25",
      "tournamentId": 21671,
      "tournamentName": "Chisinau Challenger",
      "opponentId": 43952,
      "opponentName": "Nathaniel Lammons",
      "won": true,
      "result": "7-6(2) 6-4"
    },
    {
      "id": "1264425",
      "date": "2026-05-24",
      "tournamentId": 21671,
      "tournamentName": "Chisinau Challenger",
      "opponentId": 67981,
      "opponentName": "Andrew Paulson",
      "won": true,
      "result": "6-3 6-3"
    },
    {
      "id": "1259667",
      "date": "2026-04-26",
      "tournamentId": 21607,
      "tournamentName": "Mauthausen Challenger",
      "opponentId": 18669,
      "opponentName": "David Jorda Sanchis",
      "won": false,
      "result": "6-1 6-2"
    },
    {
      "id": "1252350",
      "date": "2026-03-09",
      "tournamentId": 21505,
      "tournamentName": "Kigali 2 Challenger",
      "opponentId": 24875,
      "opponentName": "Guy Orly Iradukunda",
      "won": false,
      "result": "6-1 7-5"
    },
    {
      "id": "1252342",
      "date": "2026-03-08",
      "tournamentId": 21505,
      "tournamentName": "Kigali 2 Challenger",
      "opponentId": 44990,
      "opponentName": "Michiel De Krom",
      "won": true,
      "result": "3-6 7-6(8) 6-3"
    },
    {
      "id": "1221846",
      "date": "2025-09-29",
      "tournamentId": 21015,
      "tournamentName": "Braga Challenger",
      "opponentId": 54146,
      "opponentName": "Buvaysar Gadamauri",
      "won": false,
      "result": "7-5 6-2"
    },
    {
      "id": "1221524",
      "date": "2025-09-21",
      "tournamentId": 21010,
      "tournamentName": "Lisbon Challenger",
      "opponentId": 21464,
      "opponentName": "Alexander Ritschard",
      "won": false,
      "result": "6-2 6-2"
    },
    {
      "id": "1214753",
      "date": "2025-08-24",
      "tournamentId": 20919,
      "tournamentName": "Como Challenger",
      "opponentId": 48442,
      "opponentName": "Rudolf Molleker",
      "won": false,
      "result": "6-4 6-4"
    },
    {
      "id": "1214556",
      "date": "2025-08-17",
      "tournamentId": 20916,
      "tournamentName": "Sofia 2 Challenger",
      "opponentId": 28346,
      "opponentName": "Nino Serdarusic",
      "won": false,
      "result": "6-3 6-3"
    }
  ],
  "Hard": [
    {
      "id": "1228658",
      "date": "2025-10-27",
      "tournamentId": 21125,
      "tournamentName": "Monastir Challenger",
      "opponentId": 10828,
      "opponentName": "Radu Albot",
      "won": false,
      "result": "6-4 6-2"
    },
    {
      "id": "1228678",
      "date": "2025-10-26",
      "tournamentId": 21125,
      "tournamentName": "Monastir Challenger",
      "opponentId": 66500,
      "opponentName": "Samir Hamza Reguig",
      "won": true,
      "result": "6-4 4-6 6-4"
    },
    {
      "id": "1213946",
      "date": "2025-08-03",
      "tournamentId": 20906,
      "tournamentName": "Grodzisk Mazowiecki Challenger",
      "opponentId": 82696,
      "opponentName": "Maximus Jones",
      "won": false,
      "result": "6-4 6-4"
    },
    {
      "id": "1183547",
      "date": "2025-03-09",
      "tournamentId": 20516,
      "tournamentName": "Hersonissos 2 Challenger",
      "opponentId": 56211,
      "opponentName": "Keegan Smith",
      "won": false,
      "result": "6-3 7-6(6)"
    },
    {
      "id": "1181995",
      "date": "2025-02-23",
      "tournamentId": 20470,
      "tournamentName": "M25 Faro 1",
      "opponentId": 117365,
      "opponentName": "Goncalo Da Rosa Castro",
      "won": false,
      "result": "6-2 6-3"
    },
    {
      "id": "1181102",
      "date": "2025-02-18",
      "tournamentId": 20459,
      "tournamentName": "M25 Vila Real de Santo Antonio 2",
      "opponentId": 53726,
      "opponentName": "Cezar Cretu",
      "won": false,
      "result": "6-3 6-7(3) 6-2"
    },
    {
      "id": "1181119",
      "date": "2025-02-17",
      "tournamentId": 20459,
      "tournamentName": "M25 Vila Real de Santo Antonio 2",
      "opponentId": 88336,
      "opponentName": "Joe Leather",
      "won": true,
      "result": "2-6 6-2 10-8"
    },
    {
      "id": "1181145",
      "date": "2025-02-16",
      "tournamentId": 20459,
      "tournamentName": "M25 Vila Real de Santo Antonio 2",
      "opponentId": 117367,
      "opponentName": "Ivar Vinke",
      "won": true,
      "result": "6-3 6-0"
    },
    {
      "id": "1167823",
      "date": "2024-12-01",
      "tournamentId": 20276,
      "tournamentName": "M15 Sharm ElSheikh 19",
      "opponentId": 85868,
      "opponentName": "Jakub Kroslak",
      "won": false,
      "result": "6-4 7-5"
    },
    {
      "id": "1167480",
      "date": "2024-11-29",
      "tournamentId": 20272,
      "tournamentName": "M15 Sharm ElSheikh 18",
      "opponentId": 80222,
      "opponentName": "Evgeny Philippov",
      "won": false,
      "result": "7-6(4) 6-1"
    }
  ],
  "Grass": [],
  "updatedAt": 1782684504289,
  "playerName": "Stefan Latinovic"
}