{
  "Clay": [
    {
      "id": "1109916",
      "date": "2024-01-24",
      "tournamentId": 19476,
      "tournamentName": "M15+H Bagnoles de l'Orne 1",
      "opponentId": 34103,
      "opponentName": "Corentin Denolly",
      "won": false,
      "result": "6-2 6-3"
    },
    {
      "id": "1109918",
      "date": "2024-01-22",
      "tournamentId": 19476,
      "tournamentName": "M15+H Bagnoles de l'Orne 1",
      "opponentId": 44773,
      "opponentName": "Nathan Seateun",
      "won": true,
      "result": "7-6(1) 6-1"
    },
    {
      "id": "1109956",
      "date": "2024-01-21",
      "tournamentId": 19476,
      "tournamentName": "M15+H Bagnoles de l'Orne 1",
      "opponentId": 102808,
      "opponentName": "Guillaume Aubry",
      "won": true,
      "result": "7-5 6-4"
    },
    {
      "id": "940302",
      "date": "2022-06-15",
      "tournamentId": 17943,
      "tournamentName": "M25 Grasse 1",
      "opponentId": 29663,
      "opponentName": "Alvaro Lopez San Martin",
      "won": false,
      "result": "6-3 6-2"
    },
    {
      "id": "940294",
      "date": "2022-06-13",
      "tournamentId": 17943,
      "tournamentName": "M25 Grasse 1",
      "opponentId": 38391,
      "opponentName": "Mikalai Haliak",
      "won": true,
      "result": "6-3 6-0"
    },
    {
      "id": "940304",
      "date": "2022-06-13",
      "tournamentId": 17943,
      "tournamentName": "M25 Grasse 1",
      "opponentId": 44773,
      "opponentName": "Nathan Seateun",
      "won": true,
      "result": "1-6 6-0 10-8"
    },
    {
      "id": "940339",
      "date": "2022-06-12",
      "tournamentId": 17943,
      "tournamentName": "M25 Grasse 1",
      "opponentId": 86271,
      "opponentName": "Pierre Antoine Tailleu",
      "won": true,
      "result": "4-6 7-5 10-6"
    },
    {
      "id": "939983",
      "date": "2022-06-05",
      "tournamentId": 17939,
      "tournamentName": "M15 Cordoba 1",
      "opponentId": 94510,
      "opponentName": "Sergi Mico Fenollar",
      "won": false,
      "result": "7-6(4) 4-6 10-5"
    },
    {
      "id": "936378",
      "date": "2022-05-25",
      "tournamentId": 17891,
      "tournamentName": "M15 Oran 2",
      "opponentId": 22992,
      "opponentName": "Benjamin Lock",
      "won": false,
      "result": "6-4 6-1"
    },
    {
      "id": "936395",
      "date": "2022-05-23",
      "tournamentId": 17891,
      "tournamentName": "M15 Oran 2",
      "opponentId": 90212,
      "opponentName": "Joshua Schaefer",
      "won": true,
      "result": "6-4 6-0"
    },
    {
      "id": "935229",
      "date": "2022-05-18",
      "tournamentId": 17877,
      "tournamentName": "M15 Oran 1",
      "opponentId": 59591,
      "opponentName": "Ishaque Eqbal",
      "won": false,
      "result": "7-6(2) 6-3"
    },
    {
      "id": "935233",
      "date": "2022-05-17",
      "tournamentId": 17877,
      "tournamentName": "M15 Oran 1",
      "opponentId": 58456,
      "opponentName": "Joao Marcos Nusdeo",
      "won": true,
      "result": "5-7 7-5 6-4"
    },
    {
      "id": "916852",
      "date": "2022-01-10",
      "tournamentId": 17604,
      "tournamentName": "M15+H Bagnoles de l'Orne 1",
      "opponentId": 36522,
      "opponentName": "Cesar Bourgois",
      "won": false,
      "result": "6-1 6-3"
    },
    {
      "id": "916886",
      "date": "2022-01-09",
      "tournamentId": 17604,
      "tournamentName": "M15+H Bagnoles de l'Orne 1",
      "opponentId": 91858,
      "opponentName": "Martin Jovenin",
      "won": true,
      "result": "6-0 6-0"
    },
    {
      "id": "609041",
      "date": "2016-05-16",
      "tournamentId": 13188,
      "tournamentName": "Algeria F2",
      "opponentId": 25353,
      "opponentName": "Amine Chadli",
      "won": false,
      "result": "6-2 6-0"
    },
    {
      "id": "605633",
      "date": "2016-05-10",
      "tournamentId": 13141,
      "tournamentName": "Algeria F1",
      "opponentId": 21402,
      "opponentName": "Adria Mas Mascolo",
      "won": false,
      "result": "6-1 6-1"
    },
    {
      "id": "532133",
      "date": "2015-05-04",
      "tournamentId": 12138,
      "tournamentName": "Algeria F1",
      "opponentId": 24712,
      "opponentName": "Sagar Ahuja",
      "won": true,
      "result": "7-5 7-6(5)"
    },
    {
      "id": "532148",
      "date": "2015-05-04",
      "tournamentId": 12138,
      "tournamentName": "Algeria F1",
      "opponentId": 35563,
      "opponentName": "Yacine Benaissa",
      "won": true,
      "result": "7-5 6-2"
    },
    {
      "id": "532152",
      "date": "2015-05-04",
      "tournamentId": 12138,
      "tournamentName": "Algeria F1",
      "opponentId": 25757,
      "opponentName": "Jonathan Kanar",
      "won": false,
      "result": "6-0 6-0"
    }
  ],
  "Hard": [
    {
      "id": "10832331",
      "date": "2026-05-08",
      "tournamentId": 21682,
      "tournamentName": "M15 Monastir",
      "opponentId": 95687,
      "opponentName": "Amine Jamji",
      "won": true,
      "result": "6-1 6-1"
    },
    {
      "id": "1263622",
      "date": "2026-05-07",
      "tournamentId": 21682,
      "tournamentName": "M15 Monastir",
      "opponentId": 56190,
      "opponentName": "Mohamed Ali Abibsi",
      "won": true,
      "result": "6-3 6-3"
    },
    {
      "id": "1263647",
      "date": "2026-05-06",
      "tournamentId": 21682,
      "tournamentName": "M15 Monastir",
      "opponentId": 107899,
      "opponentName": "Gilberto Ravasio",
      "won": true,
      "result": "6-0 6-4"
    },
    {
      "id": "1262618",
      "date": "2026-05-03",
      "tournamentId": 21651,
      "tournamentName": "M15 Monastir",
      "opponentId": 48631,
      "opponentName": "Luca Wiedenmann",
      "won": false,
      "result": "6-4 6-7(6) 6-2"
    },
    {
      "id": "1262622",
      "date": "2026-05-02",
      "tournamentId": 21651,
      "tournamentName": "M15 Monastir",
      "opponentId": 54553,
      "opponentName": "Gabriele Bosio",
      "won": true,
      "result": "6-1 6-4"
    },
    {
      "id": "1262639",
      "date": "2026-05-01",
      "tournamentId": 21651,
      "tournamentName": "M15 Monastir",
      "opponentId": 92640,
      "opponentName": "Jacob Bradshaw",
      "won": true,
      "result": "7-6(6) 6-4"
    },
    {
      "id": "1262624",
      "date": "2026-04-30",
      "tournamentId": 21651,
      "tournamentName": "M15 Monastir",
      "opponentId": 59139,
      "opponentName": "Milledge Cossu",
      "won": true,
      "result": "6-1 6-2"
    },
    {
      "id": "1262664",
      "date": "2026-04-29",
      "tournamentId": 21651,
      "tournamentName": "M15 Monastir",
      "opponentId": 112585,
      "opponentName": "Filippo Callerio",
      "won": true,
      "result": "6-4 6-2"
    },
    {
      "id": "1261376",
      "date": "2026-04-25",
      "tournamentId": 21635,
      "tournamentName": "M15 Monastir",
      "opponentId": 70909,
      "opponentName": "Fausto Tabacco",
      "won": true,
      "result": "7-6(6) 1-6 6-4"
    },
    {
      "id": "1261390",
      "date": "2026-04-24",
      "tournamentId": 21635,
      "tournamentName": "M15 Monastir",
      "opponentId": 92640,
      "opponentName": "Jacob Bradshaw",
      "won": true,
      "result": "7-6(7) 6-4"
    },
    {
      "id": "1261393",
      "date": "2026-04-22",
      "tournamentId": 21635,
      "tournamentName": "M15 Monastir",
      "opponentId": 93889,
      "opponentName": "Aaron Gil Garcia",
      "won": true,
      "result": "6-3 4-6 7-6(3)"
    },
    {
      "id": "1260413",
      "date": "2026-04-18",
      "tournamentId": 21623,
      "tournamentName": "M15 Monastir",
      "opponentId": 65253,
      "opponentName": "Sebastian Gima",
      "won": false,
      "result": "3-6 6-1 6-4"
    },
    {
      "id": "1260419",
      "date": "2026-04-17",
      "tournamentId": 21623,
      "tournamentName": "M15 Monastir",
      "opponentId": 61255,
      "opponentName": "Nicolas Tepmahc",
      "won": true,
      "result": "6-4 6-2"
    },
    {
      "id": "1260454",
      "date": "2026-04-16",
      "tournamentId": 21623,
      "tournamentName": "M15 Monastir",
      "opponentId": 109474,
      "opponentName": "Hiromasa Koyama",
      "won": true,
      "result": "7-6(5) 6-2"
    },
    {
      "id": "1260424",
      "date": "2026-04-15",
      "tournamentId": 21623,
      "tournamentName": "M15 Monastir",
      "opponentId": 72609,
      "opponentName": "Matic Dimic",
      "won": true,
      "result": "6-3 6-3"
    },
    {
      "id": "1259869",
      "date": "2026-04-09",
      "tournamentId": 21617,
      "tournamentName": "M15 Monastir",
      "opponentId": 77835,
      "opponentName": "John Hallquist Lithen",
      "won": false,
      "result": "6-3 6-3"
    },
    {
      "id": "1259915",
      "date": "2026-04-07",
      "tournamentId": 21617,
      "tournamentName": "M15 Monastir",
      "opponentId": 111771,
      "opponentName": "Tobiasz Sopolinski",
      "won": true,
      "result": "6-3 6-1"
    },
    {
      "id": "1257800",
      "date": "2026-04-02",
      "tournamentId": 21586,
      "tournamentName": "M15 Monastir 11",
      "opponentId": 69536,
      "opponentName": "Tiago Torres",
      "won": false,
      "result": "2-6 6-4 6-1"
    },
    {
      "id": "1254796",
      "date": "2026-03-12",
      "tournamentId": 21548,
      "tournamentName": "M15 Monastir 8",
      "opponentId": 101054,
      "opponentName": "Kasra Rahmani",
      "won": false,
      "result": "7-5 3-6 6-4"
    },
    {
      "id": "1254842",
      "date": "2026-03-11",
      "tournamentId": 21548,
      "tournamentName": "M15 Monastir 8",
      "opponentId": 99808,
      "opponentName": "Alaa Trifi",
      "won": true,
      "result": "7-5 7-5"
    },
    {
      "id": "1253702",
      "date": "2026-03-05",
      "tournamentId": 21534,
      "tournamentName": "M15 Monastir 7",
      "opponentId": 105357,
      "opponentName": "Michele Mecarelli",
      "won": false,
      "result": "1-6 6-2 6-3"
    },
    {
      "id": "1253737",
      "date": "2026-03-04",
      "tournamentId": 21534,
      "tournamentName": "M15 Monastir 7",
      "opponentId": 96302,
      "opponentName": "Nikolai Barsukov",
      "won": true,
      "result": "2-6 6-4 6-1"
    },
    {
      "id": "1251106",
      "date": "2026-02-28",
      "tournamentId": 21470,
      "tournamentName": "M15 Monastir 6",
      "opponentId": 95668,
      "opponentName": "Andrea De Marchi",
      "won": false,
      "result": "6-2 6-1"
    },
    {
      "id": "1251122",
      "date": "2026-02-27",
      "tournamentId": 21470,
      "tournamentName": "M15 Monastir 6",
      "opponentId": 81959,
      "opponentName": "Luca Castagnola",
      "won": true,
      "result": "6-1 1-6 6-1"
    },
    {
      "id": "1251129",
      "date": "2026-02-26",
      "tournamentId": 21470,
      "tournamentName": "M15 Monastir 6",
      "opponentId": 85326,
      "opponentName": "Liam Branger",
      "won": true,
      "result": "7-6(7) 7-6(2)"
    },
    {
      "id": "1251140",
      "date": "2026-02-25",
      "tournamentId": 21470,
      "tournamentName": "M15 Monastir 6",
      "opponentId": 95593,
      "opponentName": "Reda Bennani",
      "won": true,
      "result": "3-0 ret."
    },
    {
      "id": "1249108",
      "date": "2026-02-13",
      "tournamentId": 21445,
      "tournamentName": "M25 Monastir 4",
      "opponentId": 79634,
      "opponentName": "Eliakim Coulibaly",
      "won": false,
      "result": "6-1 6-2"
    },
    {
      "id": "1249112",
      "date": "2026-02-12",
      "tournamentId": 21445,
      "tournamentName": "M25 Monastir 4",
      "opponentId": 57038,
      "opponentName": "John Echeverria",
      "won": true,
      "result": "6-1 6-4"
    },
    {
      "id": "1249182",
      "date": "2026-02-11",
      "tournamentId": 21445,
      "tournamentName": "M25 Monastir 4",
      "opponentId": 123846,
      "opponentName": "Alessandro Barbieri",
      "won": true,
      "result": "6-3 6-1"
    },
    {
      "id": "1248501",
      "date": "2026-02-08",
      "tournamentId": 21438,
      "tournamentName": "M15 Monastir 3",
      "opponentId": 61255,
      "opponentName": "Nicolas Tepmahc",
      "won": false,
      "result": "6-1 4-6 6-0"
    },
    {
      "id": "1248516",
      "date": "2026-02-08",
      "tournamentId": 21438,
      "tournamentName": "M15 Monastir 3",
      "opponentId": 86348,
      "opponentName": "Gerard Campana Lee",
      "won": true,
      "result": "6-4 5-7 6-0"
    },
    {
      "id": "1248515",
      "date": "2026-02-06",
      "tournamentId": 21438,
      "tournamentName": "M15 Monastir 3",
      "opponentId": 81412,
      "opponentName": "Cesar Bouchelaghem",
      "won": true,
      "result": "6-3 6-4"
    },
    {
      "id": "1248531",
      "date": "2026-02-05",
      "tournamentId": 21438,
      "tournamentName": "M15 Monastir 3",
      "opponentId": 107337,
      "opponentName": "Yuto Oki",
      "won": true,
      "result": "7-6(4) 6-4"
    },
    {
      "id": "1248540",
      "date": "2026-02-04",
      "tournamentId": 21438,
      "tournamentName": "M15 Monastir 3",
      "opponentId": 114186,
      "opponentName": "Mouadh Dhaouadi",
      "won": true,
      "result": "6-0 6-1"
    },
    {
      "id": "1246727",
      "date": "2026-01-28",
      "tournamentId": 21412,
      "tournamentName": "M15 Monastir 2",
      "opponentId": 76126,
      "opponentName": "Keisuke Saitoh",
      "won": false,
      "result": "6-0 6-1"
    },
    {
      "id": "1245951",
      "date": "2026-01-23",
      "tournamentId": 21402,
      "tournamentName": "M15 Monastir 1",
      "opponentId": 58432,
      "opponentName": "Oleksandr Ovcharenko",
      "won": false,
      "result": "6-1 5-0 ret."
    },
    {
      "id": "1245977",
      "date": "2026-01-23",
      "tournamentId": 21402,
      "tournamentName": "M15 Monastir 1",
      "opponentId": 83696,
      "opponentName": "Leo Borg",
      "won": true,
      "result": "3-6 6-4 6-3"
    },
    {
      "id": "1246001",
      "date": "2026-01-22",
      "tournamentId": 21402,
      "tournamentName": "M15 Monastir 1",
      "opponentId": 100201,
      "opponentName": "Tianhui Zhang",
      "won": true,
      "result": "6-2 6-1"
    },
    {
      "id": "1239196",
      "date": "2025-12-06",
      "tournamentId": 21261,
      "tournamentName": "M15 Monastir 44",
      "opponentId": 84941,
      "opponentName": "Dimitris Sakellaridis",
      "won": false,
      "result": "6-2 6-3"
    },
    {
      "id": "1239206",
      "date": "2025-12-05",
      "tournamentId": 21261,
      "tournamentName": "M15 Monastir 44",
      "opponentId": 66500,
      "opponentName": "Samir Hamza Reguig",
      "won": true,
      "result": "6-4 6-3"
    },
    {
      "id": "1239203",
      "date": "2025-12-04",
      "tournamentId": 21261,
      "tournamentName": "M15 Monastir 44",
      "opponentId": 59165,
      "opponentName": "Nikolay Vylegzhanin",
      "won": true,
      "result": "6-3 6-4"
    },
    {
      "id": "1239239",
      "date": "2025-12-03",
      "tournamentId": 21261,
      "tournamentName": "M15 Monastir 44",
      "opponentId": 104106,
      "opponentName": "Matei Todoran",
      "won": true,
      "result": "6-3 6-0"
    },
    {
      "id": "1238780",
      "date": "2025-11-26",
      "tournamentId": 21256,
      "tournamentName": "M15 Monastir 43",
      "opponentId": 68977,
      "opponentName": "Noah Lopez",
      "won": false,
      "result": "3-6 6-2 6-0"
    },
    {
      "id": "1237553",
      "date": "2025-11-21",
      "tournamentId": 21242,
      "tournamentName": "M15 Monastir 42",
      "opponentId": 67985,
      "opponentName": "Chen Dong",
      "won": false,
      "result": "1-6 6-4 6-0"
    },
    {
      "id": "1237592",
      "date": "2025-11-20",
      "tournamentId": 21242,
      "tournamentName": "M15 Monastir 42",
      "opponentId": 97972,
      "opponentName": "Theo Herrmann",
      "won": true,
      "result": "7-6(3) 3-6 6-3"
    },
    {
      "id": "1237550",
      "date": "2025-11-19",
      "tournamentId": 21242,
      "tournamentName": "M15 Monastir 42",
      "opponentId": 30692,
      "opponentName": "Francesco Ferrari",
      "won": true,
      "result": "2-6 6-4 6-3"
    },
    {
      "id": "1235843",
      "date": "2025-11-12",
      "tournamentId": 21221,
      "tournamentName": "M25 Monastir 10",
      "opponentId": 8741,
      "opponentName": "Sergey Betov",
      "won": false,
      "result": "6-1 6-7(2) 6-3"
    },
    {
      "id": "1232171",
      "date": "2025-10-30",
      "tournamentId": 21169,
      "tournamentName": "M15 Monastir 41",
      "opponentId": 47534,
      "opponentName": "Arvid Nordquist",
      "won": false,
      "result": "6-3 6-2"
    },
    {
      "id": "1232198",
      "date": "2025-10-29",
      "tournamentId": 21169,
      "tournamentName": "M15 Monastir 41",
      "opponentId": 87755,
      "opponentName": "Maximilian Figl",
      "won": true,
      "result": "6-3 1-6 6-3"
    },
    {
      "id": "1230868",
      "date": "2025-10-23",
      "tournamentId": 21154,
      "tournamentName": "M15 Monastir 40",
      "opponentId": 48631,
      "opponentName": "Luca Wiedenmann",
      "won": false,
      "result": "6-1 6-3"
    },
    {
      "id": "1230875",
      "date": "2025-10-22",
      "tournamentId": 21154,
      "tournamentName": "M15 Monastir 40",
      "opponentId": 52357,
      "opponentName": "Isaac Nortie Nortey",
      "won": true,
      "result": "6-1 6-2"
    },
    {
      "id": "1229854",
      "date": "2025-10-16",
      "tournamentId": 21141,
      "tournamentName": "M15 Monastir 39",
      "opponentId": 59723,
      "opponentName": "Jorge Plans",
      "won": false,
      "result": "6-3 6-2"
    },
    {
      "id": "1229873",
      "date": "2025-10-15",
      "tournamentId": 21141,
      "tournamentName": "M15 Monastir 39",
      "opponentId": 87431,
      "opponentName": "Lorenzo Angelini",
      "won": true,
      "result": "3-6 6-3 6-4"
    },
    {
      "id": "1227028",
      "date": "2025-10-01",
      "tournamentId": 21081,
      "tournamentName": "M15 Monastir 37",
      "opponentId": 84712,
      "opponentName": "Seydina Andre",
      "won": false,
      "result": "4-6 6-3 6-2"
    },
    {
      "id": "1226199",
      "date": "2025-09-23",
      "tournamentId": 21070,
      "tournamentName": "M15 Monastir 36",
      "opponentId": 96543,
      "opponentName": "Louis Larue",
      "won": false,
      "result": "6-4 4-6 6-3"
    },
    {
      "id": "1224837",
      "date": "2025-09-19",
      "tournamentId": 21053,
      "tournamentName": "M15 Monastir 35",
      "opponentId": 40820,
      "opponentName": "Benjamin Pietri",
      "won": false,
      "result": "6-4 7-6(3)"
    },
    {
      "id": "1224886",
      "date": "2025-09-18",
      "tournamentId": 21053,
      "tournamentName": "M15 Monastir 35",
      "opponentId": 108591,
      "opponentName": "Amir Omarkhanov",
      "won": true,
      "result": "6-1 6-4"
    },
    {
      "id": "1224876",
      "date": "2025-09-17",
      "tournamentId": 21053,
      "tournamentName": "M15 Monastir 35",
      "opponentId": 94055,
      "opponentName": "Manas Manoj Dhamne",
      "won": true,
      "result": "6-3 1-6 6-4"
    },
    {
      "id": "1223933",
      "date": "2025-09-13",
      "tournamentId": 21042,
      "tournamentName": "M15 Monastir 34",
      "opponentId": 81412,
      "opponentName": "Cesar Bouchelaghem",
      "won": false,
      "result": "7-6(5) 6-1"
    },
    {
      "id": "1223962",
      "date": "2025-09-12",
      "tournamentId": 21042,
      "tournamentName": "M15 Monastir 34",
      "opponentId": 88213,
      "opponentName": "Oskar Brostrom Poulsen",
      "won": true,
      "result": "6-1 1-6 7-6(7)"
    },
    {
      "id": "1223996",
      "date": "2025-09-11",
      "tournamentId": 21042,
      "tournamentName": "M15 Monastir 34",
      "opponentId": 121196,
      "opponentName": "Tomas Jordi Leston",
      "won": true,
      "result": "6-3 6-1"
    },
    {
      "id": "1223942",
      "date": "2025-09-10",
      "tournamentId": 21042,
      "tournamentName": "M15 Monastir 34",
      "opponentId": 57038,
      "opponentName": "John Echeverria",
      "won": true,
      "result": "6-1 6-3"
    },
    {
      "id": "1222604",
      "date": "2025-09-06",
      "tournamentId": 21026,
      "tournamentName": "M15 Monastir 33",
      "opponentId": 92640,
      "opponentName": "Jacob Bradshaw",
      "won": false,
      "result": "6-7(6) 6-2 6-1"
    },
    {
      "id": "1222608",
      "date": "2025-09-05",
      "tournamentId": 21026,
      "tournamentName": "M15 Monastir 33",
      "opponentId": 45300,
      "opponentName": "Aziz Ouakaa",
      "won": true,
      "result": "7-5 4-6 6-0"
    },
    {
      "id": "1222601",
      "date": "2025-09-04",
      "tournamentId": 21026,
      "tournamentName": "M15 Monastir 33",
      "opponentId": 31320,
      "opponentName": "Jesse Flores",
      "won": true,
      "result": "2-6 6-3 6-3"
    },
    {
      "id": "1222613",
      "date": "2025-09-02",
      "tournamentId": 21026,
      "tournamentName": "M15 Monastir 33",
      "opponentId": 57231,
      "opponentName": "Loic Namigandet Tenguere",
      "won": true,
      "result": "6-4 1-6 6-3"
    },
    {
      "id": "1219691",
      "date": "2025-08-29",
      "tournamentId": 20982,
      "tournamentName": "M15 Monastir 32",
      "opponentId": 83521,
      "opponentName": "Lui Maxted",
      "won": false,
      "result": "6-4 4-6 6-0"
    },
    {
      "id": "1219733",
      "date": "2025-08-28",
      "tournamentId": 20982,
      "tournamentName": "M15 Monastir 32",
      "opponentId": 99740,
      "opponentName": "Ivan Gretskiy",
      "won": true,
      "result": "6-3 7-5"
    },
    {
      "id": "1219723",
      "date": "2025-08-27",
      "tournamentId": 20982,
      "tournamentName": "M15 Monastir 32",
      "opponentId": 90388,
      "opponentName": "Ibrahim Snoussi",
      "won": true,
      "result": "6-0 6-0"
    },
    {
      "id": "1213533",
      "date": "2025-07-30",
      "tournamentId": 20900,
      "tournamentName": "M15 Monastir 30",
      "opponentId": 54812,
      "opponentName": "Maxence Bertimon",
      "won": false,
      "result": "6-4 7-6(3)"
    },
    {
      "id": "1209924",
      "date": "2025-07-13",
      "tournamentId": 20855,
      "tournamentName": "M15 Monastir 27",
      "opponentId": 86083,
      "opponentName": "Karan Singh",
      "won": false,
      "result": "6-0 6-2"
    },
    {
      "id": "1209957",
      "date": "2025-07-12",
      "tournamentId": 20855,
      "tournamentName": "M15 Monastir 27",
      "opponentId": 87626,
      "opponentName": "Cooper Williams",
      "won": true,
      "result": "6-2 7-5"
    },
    {
      "id": "1209937",
      "date": "2025-07-11",
      "tournamentId": 20855,
      "tournamentName": "M15 Monastir 27",
      "opponentId": 71646,
      "opponentName": "Isaac Becroft",
      "won": true,
      "result": "6-2 6-2"
    },
    {
      "id": "1209954",
      "date": "2025-07-08",
      "tournamentId": 20855,
      "tournamentName": "M15 Monastir 27",
      "opponentId": 86064,
      "opponentName": "Cian Maguire",
      "won": true,
      "result": "6-2 6-1"
    },
    {
      "id": "1207049",
      "date": "2025-07-03",
      "tournamentId": 20815,
      "tournamentName": "M15 Monastir 26",
      "opponentId": 27539,
      "opponentName": "Mohamed Nazim Makhlouf",
      "won": false,
      "result": "4-2 ret."
    },
    {
      "id": "1207077",
      "date": "2025-07-02",
      "tournamentId": 20815,
      "tournamentName": "M15 Monastir 26",
      "opponentId": 83921,
      "opponentName": "Alejandro Manzanera Pertusa",
      "won": true,
      "result": "5-7 6-4 6-4"
    },
    {
      "id": "1207079",
      "date": "2025-07-01",
      "tournamentId": 20815,
      "tournamentName": "M15 Monastir 26",
      "opponentId": 86064,
      "opponentName": "Cian Maguire",
      "won": true,
      "result": "6-2 6-1"
    },
    {
      "id": "1207117",
      "date": "2025-06-30",
      "tournamentId": 20815,
      "tournamentName": "M15 Monastir 26",
      "opponentId": 111537,
      "opponentName": "Maximillian Relic",
      "won": true,
      "result": "6-3 6-1"
    },
    {
      "id": "1207056",
      "date": "2025-06-29",
      "tournamentId": 20815,
      "tournamentName": "M15 Monastir 26",
      "opponentId": 59154,
      "opponentName": "Seiichiro Ichikawa",
      "won": true,
      "result": "6-0 6-1"
    },
    {
      "id": "1205567",
      "date": "2025-06-25",
      "tournamentId": 20796,
      "tournamentName": "M15 Monastir 25",
      "opponentId": 92466,
      "opponentName": "Moritz Kudernatsch",
      "won": false,
      "result": "6-3 6-4"
    },
    {
      "id": "1203999",
      "date": "2025-06-19",
      "tournamentId": 20777,
      "tournamentName": "M25 Monastir 3",
      "opponentId": 30626,
      "opponentName": "Aziz Dougaz",
      "won": false,
      "result": "6-3 6-3"
    },
    {
      "id": "1204070",
      "date": "2025-06-18",
      "tournamentId": 20777,
      "tournamentName": "M25 Monastir 3",
      "opponentId": 111542,
      "opponentName": "Reid Jarvis",
      "won": true,
      "result": "6-1 1-0 ret."
    },
    {
      "id": "1204074",
      "date": "2025-06-16",
      "tournamentId": 20777,
      "tournamentName": "M25 Monastir 3",
      "opponentId": 114054,
      "opponentName": "Riku Kato",
      "won": true,
      "result": "6-0 6-0"
    },
    {
      "id": "1204077",
      "date": "2025-06-16",
      "tournamentId": 20777,
      "tournamentName": "M25 Monastir 3",
      "opponentId": 117658,
      "opponentName": "Nahuel Nicolas Eli",
      "won": true,
      "result": "3-6 6-3 10-1"
    },
    {
      "id": "1204065",
      "date": "2025-06-15",
      "tournamentId": 20777,
      "tournamentName": "M25 Monastir 3",
      "opponentId": 110651,
      "opponentName": "Sebastian Huggins",
      "won": true,
      "result": "6-0 6-2"
    },
    {
      "id": "1203060",
      "date": "2025-06-12",
      "tournamentId": 20765,
      "tournamentName": "M15 Monastir 23",
      "opponentId": 95646,
      "opponentName": "Samuele Seghetti",
      "won": false,
      "result": "6-4 3-6 6-4"
    },
    {
      "id": "1203066",
      "date": "2025-06-11",
      "tournamentId": 20765,
      "tournamentName": "M15 Monastir 23",
      "opponentId": 59846,
      "opponentName": "Tomas Antonio Serrano Luis",
      "won": true,
      "result": "6-7(7) 6-2 6-0"
    },
    {
      "id": "1202117",
      "date": "2025-06-05",
      "tournamentId": 20753,
      "tournamentName": "M15 Monastir 22",
      "opponentId": 86070,
      "opponentName": "Leonardo Rossi",
      "won": false,
      "result": "6-3 6-4"
    },
    {
      "id": "1202148",
      "date": "2025-06-03",
      "tournamentId": 20753,
      "tournamentName": "M15 Monastir 22",
      "opponentId": 98508,
      "opponentName": "Anton Marchenko",
      "won": true,
      "result": "6-1 6-0"
    },
    {
      "id": "1193173",
      "date": "2025-04-22",
      "tournamentId": 20638,
      "tournamentName": "M15 Monastir 16",
      "opponentId": 29610,
      "opponentName": "Igor Ribeiro Marcondes",
      "won": true,
      "result": "7-5 3-6 10-6"
    },
    {
      "id": "1193185",
      "date": "2025-04-22",
      "tournamentId": 20638,
      "tournamentName": "M15 Monastir 16",
      "opponentId": 84941,
      "opponentName": "Dimitris Sakellaridis",
      "won": false,
      "result": "7-5 6-2"
    },
    {
      "id": "1193215",
      "date": "2025-04-20",
      "tournamentId": 20638,
      "tournamentName": "M15 Monastir 16",
      "opponentId": 80943,
      "opponentName": "Mihai Alexandru Coman",
      "won": true,
      "result": "5-7 7-5 10-3"
    },
    {
      "id": "1192322",
      "date": "2025-04-16",
      "tournamentId": 20628,
      "tournamentName": "M15 Monastir 15",
      "opponentId": 107371,
      "opponentName": "Oskari Paldanius",
      "won": false,
      "result": "6-7(5) 6-3 6-4"
    },
    {
      "id": "1192334",
      "date": "2025-04-14",
      "tournamentId": 20628,
      "tournamentName": "M15 Monastir 15",
      "opponentId": 56817,
      "opponentName": "Adan Freire Da Silva",
      "won": true,
      "result": "3-6 6-2 10-6"
    },
    {
      "id": "1192372",
      "date": "2025-04-14",
      "tournamentId": 20628,
      "tournamentName": "M15 Monastir 15",
      "opponentId": 93023,
      "opponentName": "Makar Krivoshchekov",
      "won": true,
      "result": "6-4 6-1"
    },
    {
      "id": "1192336",
      "date": "2025-04-13",
      "tournamentId": 20628,
      "tournamentName": "M15 Monastir 15",
      "opponentId": 59841,
      "opponentName": "Valentin De Carvalho",
      "won": true,
      "result": "6-1 2-0 ret."
    },
    {
      "id": "1191705",
      "date": "2025-04-07",
      "tournamentId": 20621,
      "tournamentName": "M15 Monastir 14",
      "opponentId": 72454,
      "opponentName": "Ammar Elamin",
      "won": false,
      "result": "6-2 6-2"
    },
    {
      "id": "1191776",
      "date": "2025-04-07",
      "tournamentId": 20621,
      "tournamentName": "M15 Monastir 14",
      "opponentId": 116725,
      "opponentName": "Maxwell Castle",
      "won": true,
      "result": "6-4 6-1"
    },
    {
      "id": "1191777",
      "date": "2025-04-06",
      "tournamentId": 20621,
      "tournamentName": "M15 Monastir 14",
      "opponentId": 116888,
      "opponentName": "Achref Ltaief",
      "won": true,
      "result": "6-0 6-0"
    },
    {
      "id": "1187161",
      "date": "2025-03-17",
      "tournamentId": 20563,
      "tournamentName": "M15 Monastir 11",
      "opponentId": 110632,
      "opponentName": "Angel Hernandez",
      "won": false,
      "result": "2-6 6-4 10-6"
    },
    {
      "id": "1187231",
      "date": "2025-03-16",
      "tournamentId": 20563,
      "tournamentName": "M15 Monastir 11",
      "opponentId": 110209,
      "opponentName": "Mert Aytekin",
      "won": true,
      "result": "6-3 6-3"
    },
    {
      "id": "1185878",
      "date": "2025-03-10",
      "tournamentId": 20548,
      "tournamentName": "M15 Monastir 10",
      "opponentId": 56400,
      "opponentName": "Thomas Deschamps",
      "won": false,
      "result": "6-2 6-4"
    },
    {
      "id": "1185947",
      "date": "2025-03-10",
      "tournamentId": 20548,
      "tournamentName": "M15 Monastir 10",
      "opponentId": 111532,
      "opponentName": "Esteban Talavera Cortes",
      "won": true,
      "result": "6-2 6-3"
    },
    {
      "id": "1185911",
      "date": "2025-03-09",
      "tournamentId": 20548,
      "tournamentName": "M15 Monastir 10",
      "opponentId": 84378,
      "opponentName": "Jasin Jakupi",
      "won": true,
      "result": "3-6 6-0 10-6"
    },
    {
      "id": "1185130",
      "date": "2025-03-05",
      "tournamentId": 20538,
      "tournamentName": "M15 Monastir 9",
      "opponentId": 34605,
      "opponentName": "Elliot Benchetrit",
      "won": false,
      "result": "6-4 6-2"
    },
    {
      "id": "1182406",
      "date": "2025-02-27",
      "tournamentId": 20475,
      "tournamentName": "M15 Monastir 8",
      "opponentId": 54965,
      "opponentName": "Charles Bertimon",
      "won": false,
      "result": "6-2 6-4"
    },
    {
      "id": "1182423",
      "date": "2025-02-24",
      "tournamentId": 20475,
      "tournamentName": "M15 Monastir 8",
      "opponentId": 67852,
      "opponentName": "Imran Sibille",
      "won": true,
      "result": "6-4 6-2"
    },
    {
      "id": "1182441",
      "date": "2025-02-24",
      "tournamentId": 20475,
      "tournamentName": "M15 Monastir 8",
      "opponentId": 87431,
      "opponentName": "Lorenzo Angelini",
      "won": true,
      "result": "7-5 6-3"
    },
    {
      "id": "1182450",
      "date": "2025-02-23",
      "tournamentId": 20475,
      "tournamentName": "M15 Monastir 8",
      "opponentId": 95490,
      "opponentName": "Nicolas Philibert",
      "won": true,
      "result": "6-1 3-2 ret."
    },
    {
      "id": "1181382",
      "date": "2025-02-16",
      "tournamentId": 20463,
      "tournamentName": "M15 Monastir 7",
      "opponentId": 106088,
      "opponentName": "Fadi Bidan",
      "won": false,
      "result": "2-6 6-4 10-6"
    },
    {
      "id": "1180591",
      "date": "2025-02-09",
      "tournamentId": 20453,
      "tournamentName": "M15 Monastir 6",
      "opponentId": 116990,
      "opponentName": "Devaharshith Neelam",
      "won": false,
      "result": "1-0 ret."
    },
    {
      "id": "1177357",
      "date": "2025-01-15",
      "tournamentId": 20414,
      "tournamentName": "M15 Monastir 2",
      "opponentId": 94966,
      "opponentName": "Matisse Bobichon",
      "won": false,
      "result": "6-3 6-4"
    },
    {
      "id": "1177380",
      "date": "2025-01-13",
      "tournamentId": 20414,
      "tournamentName": "M15 Monastir 2",
      "opponentId": 68190,
      "opponentName": "Ahmed Mouhan",
      "won": true,
      "result": "6-3 6-4"
    },
    {
      "id": "1177443",
      "date": "2025-01-12",
      "tournamentId": 20414,
      "tournamentName": "M15 Monastir 2",
      "opponentId": 116725,
      "opponentName": "Maxwell Castle",
      "won": true,
      "result": "6-1 6-2"
    },
    {
      "id": "1177067",
      "date": "2025-01-08",
      "tournamentId": 20411,
      "tournamentName": "M15 Monastir 1",
      "opponentId": 115746,
      "opponentName": "Sebastiano Cocola",
      "won": false,
      "result": "7-5 5-0 ret."
    },
    {
      "id": "1166789",
      "date": "2024-11-25",
      "tournamentId": 20264,
      "tournamentName": "M25 Monastir 4",
      "opponentId": 104612,
      "opponentName": "David Cristian Carteputreda",
      "won": false,
      "result": "7-5 6-1"
    },
    {
      "id": "1166852",
      "date": "2024-11-25",
      "tournamentId": 20264,
      "tournamentName": "M25 Monastir 4",
      "opponentId": 105358,
      "opponentName": "Mattia Ricci",
      "won": true,
      "result": "6-1 6-2"
    },
    {
      "id": "1166848",
      "date": "2024-11-24",
      "tournamentId": 20264,
      "tournamentName": "M25 Monastir 4",
      "opponentId": 104095,
      "opponentName": "Omar Hamzaoui",
      "won": true,
      "result": "6-2 6-2"
    },
    {
      "id": "1165676",
      "date": "2024-11-18",
      "tournamentId": 20251,
      "tournamentName": "M25 Monastir 3",
      "opponentId": 102640,
      "opponentName": "Rares Teodor Pieleanu",
      "won": false,
      "result": "7-5 6-4"
    },
    {
      "id": "1165684",
      "date": "2024-11-17",
      "tournamentId": 20251,
      "tournamentName": "M25 Monastir 3",
      "opponentId": 62702,
      "opponentName": "Max Van Nunen",
      "won": true,
      "result": "6-0 6-4"
    },
    {
      "id": "1164634",
      "date": "2024-11-11",
      "tournamentId": 20239,
      "tournamentName": "M15 Monastir 46",
      "opponentId": 54965,
      "opponentName": "Charles Bertimon",
      "won": false,
      "result": "6-4 1-6 10-4"
    },
    {
      "id": "1163542",
      "date": "2024-11-09",
      "tournamentId": 20224,
      "tournamentName": "M25 Monastir 2",
      "opponentId": 23298,
      "opponentName": "Kimmer Coppejans",
      "won": false,
      "result": "6-1 6-2"
    },
    {
      "id": "1163567",
      "date": "2024-11-08",
      "tournamentId": 20224,
      "tournamentName": "M25 Monastir 2",
      "opponentId": 80641,
      "opponentName": "Pietro Pampanin",
      "won": true,
      "result": "6-4 6-1"
    },
    {
      "id": "1163547",
      "date": "2024-11-07",
      "tournamentId": 20224,
      "tournamentName": "M25 Monastir 2",
      "opponentId": 60479,
      "opponentName": "Giovanni Agostinetto",
      "won": true,
      "result": "6-0 6-4"
    },
    {
      "id": "1163596",
      "date": "2024-11-07",
      "tournamentId": 20224,
      "tournamentName": "M25 Monastir 2",
      "opponentId": 100617,
      "opponentName": "Sydney Zick",
      "won": true,
      "result": "6-1 6-1"
    },
    {
      "id": "1163586",
      "date": "2024-11-04",
      "tournamentId": 20224,
      "tournamentName": "M25 Monastir 2",
      "opponentId": 93889,
      "opponentName": "Aaron Gil Garcia",
      "won": true,
      "result": "6-3 6-4"
    },
    {
      "id": "1163606",
      "date": "2024-11-04",
      "tournamentId": 20224,
      "tournamentName": "M25 Monastir 2",
      "opponentId": 106297,
      "opponentName": "Mustapha El Natour",
      "won": true,
      "result": "6-2 6-1"
    },
    {
      "id": "1163601",
      "date": "2024-11-03",
      "tournamentId": 20224,
      "tournamentName": "M25 Monastir 2",
      "opponentId": 104663,
      "opponentName": "Francisco Guimaraes 2",
      "won": true,
      "result": "6-4 6-3"
    },
    {
      "id": "1163122",
      "date": "2024-10-28",
      "tournamentId": 20218,
      "tournamentName": "M25 Monastir 1",
      "opponentId": 92341,
      "opponentName": "Liam Krall",
      "won": false,
      "result": "6-4 6-4"
    },
    {
      "id": "1160785",
      "date": "2024-10-21",
      "tournamentId": 20160,
      "tournamentName": "M15 Monastir 43",
      "opponentId": 62181,
      "opponentName": "Alex Jones",
      "won": false,
      "result": "6-3 6-2"
    },
    {
      "id": "1160806",
      "date": "2024-10-20",
      "tournamentId": 20160,
      "tournamentName": "M15 Monastir 43",
      "opponentId": 80641,
      "opponentName": "Pietro Pampanin",
      "won": true,
      "result": "6-1 2-6 10-7"
    },
    {
      "id": "1144289",
      "date": "2024-07-29",
      "tournamentId": 19936,
      "tournamentName": "M15 Monastir 31",
      "opponentId": 113232,
      "opponentName": "Landon Ardila",
      "won": false,
      "result": "6-7(2) 6-0 10-5"
    },
    {
      "id": "1144322",
      "date": "2024-07-29",
      "tournamentId": 19936,
      "tournamentName": "M15 Monastir 31",
      "opponentId": 88075,
      "opponentName": "Curzio Manucci",
      "won": true,
      "result": "6-2 6-1"
    },
    {
      "id": "1144365",
      "date": "2024-07-28",
      "tournamentId": 19936,
      "tournamentName": "M15 Monastir 31",
      "opponentId": 110739,
      "opponentName": "Mukkesh Sabaresh Vijay Shankar",
      "won": true,
      "result": "7-6 3-0 ret."
    },
    {
      "id": "1143281",
      "date": "2024-07-24",
      "tournamentId": 19923,
      "tournamentName": "M15 Monastir 30",
      "opponentId": 23335,
      "opponentName": "Yurii Dzhavakian",
      "won": false,
      "result": "2-6 6-3 6-3"
    },
    {
      "id": "1143327",
      "date": "2024-07-22",
      "tournamentId": 19923,
      "tournamentName": "M15 Monastir 30",
      "opponentId": 95490,
      "opponentName": "Nicolas Philibert",
      "won": true,
      "result": "6-3 6-1"
    },
    {
      "id": "1143331",
      "date": "2024-07-22",
      "tournamentId": 19923,
      "tournamentName": "M15 Monastir 30",
      "opponentId": 97972,
      "opponentName": "Theo Herrmann",
      "won": true,
      "result": "6-4 7-5"
    },
    {
      "id": "1143315",
      "date": "2024-07-21",
      "tournamentId": 19923,
      "tournamentName": "M15 Monastir 30",
      "opponentId": 90584,
      "opponentName": "Mehdi Ben Arab",
      "won": true,
      "result": "6-0 6-2"
    },
    {
      "id": "1142215",
      "date": "2024-07-15",
      "tournamentId": 19911,
      "tournamentName": "M15 Monastir 29",
      "opponentId": 67985,
      "opponentName": "Chen Dong",
      "won": false,
      "result": "7-5 6-1"
    },
    {
      "id": "1142214",
      "date": "2024-07-14",
      "tournamentId": 19911,
      "tournamentName": "M15 Monastir 29",
      "opponentId": 37300,
      "opponentName": "Tommaso Schold",
      "won": true,
      "result": "6-1 1-6 10-6"
    },
    {
      "id": "1044364",
      "date": "2023-07-24",
      "tournamentId": 18957,
      "tournamentName": "M15 Monastir 30",
      "opponentId": 100196,
      "opponentName": "Lorenzo Carboni",
      "won": false,
      "result": "1-6 6-1 10-8"
    },
    {
      "id": "1044413",
      "date": "2023-07-23",
      "tournamentId": 18957,
      "tournamentName": "M15 Monastir 30",
      "opponentId": 67017,
      "opponentName": "Thando Longwe-Smit",
      "won": true,
      "result": "6-4 3-6 10-1"
    },
    {
      "id": "1042221",
      "date": "2023-07-17",
      "tournamentId": 18945,
      "tournamentName": "M15 Monastir 29",
      "opponentId": 96517,
      "opponentName": "Gianluca Cadenasso",
      "won": false,
      "result": "7-5 3-0 ret."
    },
    {
      "id": "1042228",
      "date": "2023-07-17",
      "tournamentId": 18945,
      "tournamentName": "M15 Monastir 29",
      "opponentId": 49219,
      "opponentName": "Ighor Halmenschlager Reis",
      "won": true,
      "result": "7-6(2) 6-4"
    },
    {
      "id": "1042317",
      "date": "2023-07-16",
      "tournamentId": 18945,
      "tournamentName": "M15 Monastir 29",
      "opponentId": 91863,
      "opponentName": "Loann Massard",
      "won": true,
      "result": "7-6(4) 6-3"
    },
    {
      "id": "1040041",
      "date": "2023-07-09",
      "tournamentId": 18933,
      "tournamentName": "M15 Monastir 28",
      "opponentId": 95605,
      "opponentName": "Phillip Jordan",
      "won": false,
      "result": "2-6 6-2 10-4"
    },
    {
      "id": "1038092",
      "date": "2023-07-03",
      "tournamentId": 18922,
      "tournamentName": "M15 Monastir 27",
      "opponentId": 83520,
      "opponentName": "Pablo Trochu",
      "won": false,
      "result": "6-4 2-6 10-7"
    },
    {
      "id": "1038170",
      "date": "2023-07-02",
      "tournamentId": 18922,
      "tournamentName": "M15 Monastir 27",
      "opponentId": 103364,
      "opponentName": "Nikita Safonov",
      "won": true,
      "result": "6-1 6-2"
    },
    {
      "id": "1033383",
      "date": "2023-06-26",
      "tournamentId": 18886,
      "tournamentName": "M15 Monastir 26",
      "opponentId": 87767,
      "opponentName": "Oliver Tarvet",
      "won": false,
      "result": "6-2 6-0"
    },
    {
      "id": "1033450",
      "date": "2023-06-26",
      "tournamentId": 18886,
      "tournamentName": "M15 Monastir 26",
      "opponentId": 95482,
      "opponentName": "Nicolas Jadoun",
      "won": true,
      "result": "4-6 6-3 4-0 ret."
    },
    {
      "id": "1033429",
      "date": "2023-06-25",
      "tournamentId": 18886,
      "tournamentName": "M15 Monastir 26",
      "opponentId": 85959,
      "opponentName": "Beren Tan",
      "won": true,
      "result": "6-3 6-1"
    },
    {
      "id": "1031946",
      "date": "2023-06-19",
      "tournamentId": 18869,
      "tournamentName": "M15 Monastir 25",
      "opponentId": 85445,
      "opponentName": "Mikhail Gorokhov",
      "won": false,
      "result": "7-5 6-1"
    },
    {
      "id": "1032001",
      "date": "2023-06-18",
      "tournamentId": 18869,
      "tournamentName": "M15 Monastir 25",
      "opponentId": 89512,
      "opponentName": "Daniel Vecchio Couldrey Rebelo",
      "won": true,
      "result": "6-1 6-1"
    },
    {
      "id": "996965",
      "date": "2023-03-05",
      "tournamentId": 18653,
      "tournamentName": "M15 Creteil 1",
      "opponentId": 38391,
      "opponentName": "Mikalai Haliak",
      "won": false,
      "result": "6-1 6-1"
    },
    {
      "id": "984252",
      "date": "2023-01-09",
      "tournamentId": 18530,
      "tournamentName": "M15 Monastir 2",
      "opponentId": 84046,
      "opponentName": "Ivan Sodan",
      "won": false,
      "result": "7-6(2) 7-5"
    },
    {
      "id": "984262",
      "date": "2023-01-09",
      "tournamentId": 18530,
      "tournamentName": "M15 Monastir 2",
      "opponentId": 56842,
      "opponentName": "Med Anis Sakka",
      "won": true,
      "result": "6-1 6-0"
    },
    {
      "id": "984273",
      "date": "2023-01-08",
      "tournamentId": 18530,
      "tournamentName": "M15 Monastir 2",
      "opponentId": 66351,
      "opponentName": "Matteo Meneghetti",
      "won": true,
      "result": "6-3 6-2"
    },
    {
      "id": "983808",
      "date": "2023-01-02",
      "tournamentId": 18525,
      "tournamentName": "M15 Monastir 1",
      "opponentId": 99846,
      "opponentName": "Ryotaro Taguchi",
      "won": false,
      "result": "6-3 6-2"
    },
    {
      "id": "983821",
      "date": "2023-01-01",
      "tournamentId": 18525,
      "tournamentName": "M15 Monastir 1",
      "opponentId": 59841,
      "opponentName": "Valentin De Carvalho",
      "won": true,
      "result": "6-1 6-0"
    },
    {
      "id": "966133",
      "date": "2022-11-02",
      "tournamentId": 18305,
      "tournamentName": "M15 Monastir 43",
      "opponentId": 51859,
      "opponentName": "Sheng Tang",
      "won": false,
      "result": "6-1 6-4"
    },
    {
      "id": "966153",
      "date": "2022-10-31",
      "tournamentId": 18305,
      "tournamentName": "M15 Monastir 43",
      "opponentId": 74568,
      "opponentName": "Clement Deleersnyder",
      "won": true,
      "result": "2-6 6-3 10-5"
    },
    {
      "id": "966169",
      "date": "2022-10-30",
      "tournamentId": 18305,
      "tournamentName": "M15 Monastir 43",
      "opponentId": 86689,
      "opponentName": "Tobias Hajek",
      "won": true,
      "result": "6-0 6-0"
    },
    {
      "id": "965414",
      "date": "2022-10-24",
      "tournamentId": 18296,
      "tournamentName": "M15 Monastir 42",
      "opponentId": 60803,
      "opponentName": "Noel Larwig",
      "won": false,
      "result": "6-3 6-1"
    },
    {
      "id": "965442",
      "date": "2022-10-23",
      "tournamentId": 18296,
      "tournamentName": "M15 Monastir 42",
      "opponentId": 85524,
      "opponentName": "Yessine Kerouat",
      "won": true,
      "result": "6-1 6-0"
    },
    {
      "id": "954107",
      "date": "2022-08-30",
      "tournamentId": 18128,
      "tournamentName": "M15 Monastir 34",
      "opponentId": 83520,
      "opponentName": "Pablo Trochu",
      "won": false,
      "result": "4-6 6-5 ret."
    },
    {
      "id": "954138",
      "date": "2022-08-29",
      "tournamentId": 18128,
      "tournamentName": "M15 Monastir 34",
      "opponentId": 75661,
      "opponentName": "George Gregoriou",
      "won": true,
      "result": "6-0 6-4"
    },
    {
      "id": "953118",
      "date": "2022-08-21",
      "tournamentId": 18115,
      "tournamentName": "M15 Monastir 33",
      "opponentId": 92649,
      "opponentName": "Tiago Pereira",
      "won": false,
      "result": "6-7(8) 6-3 11-9"
    },
    {
      "id": "924545",
      "date": "2022-03-14",
      "tournamentId": 17710,
      "tournamentName": "M15 Poitiers 1",
      "opponentId": 36842,
      "opponentName": "Ben Jones",
      "won": false,
      "result": "6-4 6-4"
    },
    {
      "id": "924582",
      "date": "2022-03-13",
      "tournamentId": 17710,
      "tournamentName": "M15 Poitiers 1",
      "opponentId": 86010,
      "opponentName": "Martin Sabas",
      "won": true,
      "result": "6-4 6-4"
    },
    {
      "id": "924590",
      "date": "2022-03-13",
      "tournamentId": 17710,
      "tournamentName": "M15 Poitiers 1",
      "opponentId": 90626,
      "opponentName": "Luis Utrilla",
      "won": true,
      "result": "6-2 6-4"
    },
    {
      "id": "923394",
      "date": "2022-03-09",
      "tournamentId": 17697,
      "tournamentName": "M15 Creteil 1",
      "opponentId": 36470,
      "opponentName": "Mats Rosenkranz",
      "won": false,
      "result": "6-1 3-6 6-3"
    },
    {
      "id": "923426",
      "date": "2022-03-07",
      "tournamentId": 17697,
      "tournamentName": "M15 Creteil 1",
      "opponentId": 88896,
      "opponentName": "Matt Ponchet",
      "won": true,
      "result": "6-2 6-4"
    },
    {
      "id": "923433",
      "date": "2022-03-06",
      "tournamentId": 17697,
      "tournamentName": "M15 Creteil 1",
      "opponentId": 92745,
      "opponentName": "Oscar Lacides",
      "won": true,
      "result": "6-2 6-1"
    },
    {
      "id": "920903",
      "date": "2022-02-20",
      "tournamentId": 17665,
      "tournamentName": "M15 Monastir 7",
      "opponentId": 45776,
      "opponentName": "Tao Mu",
      "won": false,
      "result": "6-1 6-2"
    },
    {
      "id": "911159",
      "date": "2021-12-30",
      "tournamentId": 17514,
      "tournamentName": "M15 Monastir 50",
      "opponentId": 25810,
      "opponentName": "Skander Mansouri",
      "won": false,
      "result": "6-4 6-3"
    },
    {
      "id": "911154",
      "date": "2021-12-28",
      "tournamentId": 17514,
      "tournamentName": "M15 Monastir 50",
      "opponentId": 36059,
      "opponentName": "Milan Drinic",
      "won": true,
      "result": "6-4 6-4"
    },
    {
      "id": "560985",
      "date": "2015-08-31",
      "tournamentId": 12532,
      "tournamentName": "Turkey F35",
      "opponentId": 26953,
      "opponentName": "Rodrigo Castro Aravena",
      "won": false,
      "result": "6-0 7-5"
    }
  ],
  "Grass": [],
  "updatedAt": 1778251840124,
  "playerName": "Toufik Sahtali"
}