{
  "Clay": [
    {
      "id": "1058160",
      "date": "2023-08-30",
      "tournamentId": 19038,
      "tournamentName": "M25 Oldenzaal 1",
      "opponentId": 83223,
      "opponentName": "Daniel Merida Aguilar",
      "won": false,
      "result": "7-6(3) 6-3"
    },
    {
      "id": "1056569",
      "date": "2023-08-26",
      "tournamentId": 19029,
      "tournamentName": "M15 Trier 1",
      "opponentId": 86351,
      "opponentName": "Tom Gentzsch",
      "won": false,
      "result": "6-4 6-2"
    }
  ],
  "Hard": [
    {
      "id": "902991",
      "date": "2021-10-17",
      "tournamentId": 17408,
      "tournamentName": "M25 Hamburg 1",
      "opponentId": 84352,
      "opponentName": "Romain Faucon",
      "won": true,
      "result": "7-5 6-1"
    },
    {
      "id": "864171",
      "date": "2020-12-13",
      "tournamentId": 16870,
      "tournamentName": "M15 Monastir 21",
      "opponentId": 70909,
      "opponentName": "Fausto Tabacco",
      "won": false,
      "result": "7-6(6) 7-5"
    },
    {
      "id": "861154",
      "date": "2020-10-31",
      "tournamentId": 16816,
      "tournamentName": "Eckental Challenger",
      "opponentId": 55290,
      "opponentName": "Filip Cristian Jianu",
      "won": true,
      "result": "6-2 6-3"
    },
    {
      "id": "707317",
      "date": "2017-09-11",
      "tournamentId": 14536,
      "tournamentName": "France F19 (Mulhouse)",
      "opponentId": 44595,
      "opponentName": "Ugo Blanchet",
      "won": false,
      "result": "6-7(12) 6-2 6-4"
    }
  ],
  "Grass": [],
  "updatedAt": 1782597990171,
  "playerName": "Tom Schonenberg"
}