{
  "Clay": [
    {
      "id": "1142157",
      "date": "2024-07-16",
      "tournamentId": 19910,
      "tournamentName": "M15 Bucharest 4",
      "opponentId": 81995,
      "opponentName": "Luciano Emanuel Ambrogi",
      "won": false,
      "result": "6-1 6-1"
    },
    {
      "id": "1129270",
      "date": "2024-05-23",
      "tournamentId": 19742,
      "tournamentName": "M15 Bucharest 3",
      "opponentId": 54208,
      "opponentName": "Florent Bax",
      "won": false,
      "result": "6-1 6-4"
    },
    {
      "id": "1026550",
      "date": "2023-05-31",
      "tournamentId": 18803,
      "tournamentName": "M15 Constanta 1",
      "opponentId": 86351,
      "opponentName": "Tom Gentzsch",
      "won": false,
      "result": "6-3 6-2"
    }
  ],
  "Hard": [],
  "Grass": [],
  "updatedAt": 1781388244750,
  "playerName": "Filip Gabriel Bara"
}