{
  "Clay": [
    {
      "id": "110218861",
      "date": "2026-06-29",
      "tournamentId": 21754,
      "tournamentName": "Milan Challenger",
      "opponentId": 76010,
      "opponentName": "Daniel Rincon",
      "won": false,
      "result": "6-2 1-0 ret."
    },
    {
      "id": "1270696",
      "date": "2026-06-17",
      "tournamentId": 21745,
      "tournamentName": "Parma Challenger",
      "opponentId": 54146,
      "opponentName": "Buvaysar Gadamauri",
      "won": false,
      "result": "6-4 7-6(1)"
    },
    {
      "id": "1270442",
      "date": "2026-06-16",
      "tournamentId": 21745,
      "tournamentName": "Parma Challenger",
      "opponentId": 84083,
      "opponentName": "Ilia Simakin",
      "won": true,
      "result": "6-3 6-4"
    },
    {
      "id": "187942972",
      "date": "2026-06-03",
      "tournamentId": 21734,
      "tournamentName": "Perugia Challenger",
      "opponentId": 64896,
      "opponentName": "Pablo Llamas Ruiz",
      "won": false,
      "result": "7-6(3) 6-3"
    },
    {
      "id": "1269510",
      "date": "2026-06-02",
      "tournamentId": 21734,
      "tournamentName": "Perugia Challenger",
      "opponentId": 53726,
      "opponentName": "Cezar Cretu",
      "won": true,
      "result": "7-6(4) 6-4"
    },
    {
      "id": "1264567",
      "date": "2026-05-31",
      "tournamentId": 21673,
      "tournamentName": "Vicenza Challenger",
      "opponentId": 83314,
      "opponentName": "Lukas Neumayer",
      "won": false,
      "result": "6-2 6-2"
    },
    {
      "id": "1264516",
      "date": "2026-05-30",
      "tournamentId": 21673,
      "tournamentName": "Vicenza Challenger",
      "opponentId": 12097,
      "opponentName": "Stefano Travaglia",
      "won": true,
      "result": "7-5 7-6(5)"
    },
    {
      "id": "1264532",
      "date": "2026-05-29",
      "tournamentId": 21673,
      "tournamentName": "Vicenza Challenger",
      "opponentId": 45979,
      "opponentName": "Yu Hsiou Hsu",
      "won": true,
      "result": "6-2 6-3"
    },
    {
      "id": "1264539",
      "date": "2026-05-28",
      "tournamentId": 21673,
      "tournamentName": "Vicenza Challenger",
      "opponentId": 54380,
      "opponentName": "Tommaso Compagnucci",
      "won": true,
      "result": "2-6 6-4 6-2"
    },
    {
      "id": "1264552",
      "date": "2026-05-26",
      "tournamentId": 21673,
      "tournamentName": "Vicenza Challenger",
      "opponentId": 84710,
      "opponentName": "Giorgio Tabacco",
      "won": true,
      "result": "6-1 7-6(4)"
    }
  ],
  "Hard": [
    {
      "id": "1251755",
      "date": "2026-03-02",
      "tournamentId": 21502,
      "tournamentName": "Hersonissos 1 Challenger",
      "opponentId": 83314,
      "opponentName": "Lukas Neumayer",
      "won": false,
      "result": "6-1 3-0 ret."
    },
    {
      "id": "1249839",
      "date": "2026-02-22",
      "tournamentId": 21453,
      "tournamentName": "M25 Trento 1",
      "opponentId": 40187,
      "opponentName": "Andrea Guerrieri",
      "won": false,
      "result": "7-6(3) 7-6(4)"
    },
    {
      "id": "1249796",
      "date": "2026-02-21",
      "tournamentId": 21453,
      "tournamentName": "M25 Trento 1",
      "opponentId": 51965,
      "opponentName": "Francesco Forti",
      "won": true,
      "result": "7-6(5) 6-4"
    },
    {
      "id": "1249786",
      "date": "2026-02-20",
      "tournamentId": 21453,
      "tournamentName": "M25 Trento 1",
      "opponentId": 10014,
      "opponentName": "Mirza Basic",
      "won": true,
      "result": "6-4 6-3"
    },
    {
      "id": "1249794",
      "date": "2026-02-19",
      "tournamentId": 21453,
      "tournamentName": "M25 Trento 1",
      "opponentId": 36062,
      "opponentName": "Marek Gengel",
      "won": true,
      "result": "7-5 6-4"
    },
    {
      "id": "1249817",
      "date": "2026-02-17",
      "tournamentId": 21453,
      "tournamentName": "M25 Trento 1",
      "opponentId": 88071,
      "opponentName": "Gregor Hausberger",
      "won": true,
      "result": "7-6(4) 6-1"
    },
    {
      "id": "1247692",
      "date": "2026-02-09",
      "tournamentId": 21424,
      "tournamentName": "Tenerife 2 Challenger",
      "opponentId": 46422,
      "opponentName": "Jacopo Berrettini",
      "won": false,
      "result": "6-3 6-3"
    },
    {
      "id": "1247374",
      "date": "2026-02-04",
      "tournamentId": 21419,
      "tournamentName": "Tenerife 1 Challenger",
      "opponentId": 63016,
      "opponentName": "George Loffhagen",
      "won": false,
      "result": "7-5 6-3"
    },
    {
      "id": "1247354",
      "date": "2026-02-03",
      "tournamentId": 21419,
      "tournamentName": "Tenerife 1 Challenger",
      "opponentId": 78285,
      "opponentName": "Dali Blanch",
      "won": true,
      "result": "7-6(5) 3-6 7-6(5)"
    },
    {
      "id": "1228012",
      "date": "2025-10-12",
      "tournamentId": 21114,
      "tournamentName": "Shenzhen Challenger",
      "opponentId": 54358,
      "opponentName": "Ye Cong Mo",
      "won": false,
      "result": "6-4 5-7 7-6(10)"
    }
  ],
  "Grass": [],
  "updatedAt": 1783720847508,
  "playerName": "Jacopo Vasami"
}