{
  "Clay": [
    {
      "id": "157498617",
      "date": "2026-05-26",
      "tournamentId": 21329,
      "tournamentName": "French Open - Paris",
      "opponentId": 83795,
      "opponentName": "Jaime Faria",
      "won": false,
      "result": "6-4 7-5 6-4"
    },
    {
      "id": "1243227",
      "date": "2026-05-07",
      "tournamentId": 21326,
      "tournamentName": "Internazionali BNL d'Italia - Rome",
      "opponentId": 66828,
      "opponentName": "Mariano Navone",
      "won": false,
      "result": "6-4 6-2"
    },
    {
      "id": "1243069",
      "date": "2026-04-25",
      "tournamentId": 21325,
      "tournamentName": "Mutua Madrid Open - Madrid",
      "opponentId": 104215,
      "opponentName": "Nicolai Budkov Kjaer",
      "won": false,
      "result": "6-2 6-1"
    },
    {
      "id": "1242980",
      "date": "2026-04-17",
      "tournamentId": 21324,
      "tournamentName": "BMW Open - Munich",
      "opponentId": 34539,
      "opponentName": "Alex Molcan",
      "won": false,
      "result": "6-4 6-4"
    },
    {
      "id": "1242989",
      "date": "2026-04-16",
      "tournamentId": 21324,
      "tournamentName": "BMW Open - Munich",
      "opponentId": 52140,
      "opponentName": "Fabian Marozsan",
      "won": true,
      "result": "7-6(4) 6-2"
    },
    {
      "id": "1242981",
      "date": "2026-04-14",
      "tournamentId": 21324,
      "tournamentName": "BMW Open - Munich",
      "opponentId": 33860,
      "opponentName": "Tallon Griekspoor",
      "won": true,
      "result": "6-4 3-6 6-2"
    },
    {
      "id": "1242831",
      "date": "2026-04-06",
      "tournamentId": 21322,
      "tournamentName": "Monte-Carlo Rolex Masters - Monte-Carlo",
      "opponentId": 88766,
      "opponentName": "Alexander Blockx",
      "won": false,
      "result": "6-4 4-6 6-3"
    },
    {
      "id": "1171858",
      "date": "2025-05-29",
      "tournamentId": 20340,
      "tournamentName": "French Open - Paris",
      "opponentId": 51417,
      "opponentName": "Filip Misolic",
      "won": false,
      "result": "7-6(5) 7-6(6) 4-6 4-6 6-3"
    },
    {
      "id": "1171825",
      "date": "2025-05-26",
      "tournamentId": 20340,
      "tournamentName": "French Open - Paris",
      "opponentId": 27358,
      "opponentName": "Pedro Martinez Portero",
      "won": true,
      "result": "6-2 6-0 6-3"
    },
    {
      "id": "1171539",
      "date": "2025-05-09",
      "tournamentId": 20337,
      "tournamentName": "Internazionali BNL d'Italia - Rome",
      "opponentId": 79088,
      "opponentName": "Vilius Gaubas",
      "won": false,
      "result": "6-3 6-4"
    }
  ],
  "Hard": [
    {
      "id": "1242516",
      "date": "2026-03-19",
      "tournamentId": 21318,
      "tournamentName": "Miami Open - Miami",
      "opponentId": 24249,
      "opponentName": "Botic Van De Zandschulp",
      "won": false,
      "result": "7-5 6-3"
    },
    {
      "id": "1242354",
      "date": "2026-03-08",
      "tournamentId": 21317,
      "tournamentName": "BNP Paribas Open - Indian Wells",
      "opponentId": 47275,
      "opponentName": "Jannik Sinner",
      "won": false,
      "result": "6-3 6-2"
    },
    {
      "id": "1242366",
      "date": "2026-03-06",
      "tournamentId": 21317,
      "tournamentName": "BNP Paribas Open - Indian Wells",
      "opponentId": 37532,
      "opponentName": "Tomas Martin Etcheverry",
      "won": true,
      "result": "6-3 2-6 7-6(5)"
    },
    {
      "id": "1242351",
      "date": "2026-03-04",
      "tournamentId": 21317,
      "tournamentName": "BNP Paribas Open - Indian Wells",
      "opponentId": 30470,
      "opponentName": "Stefanos Tsitsipas",
      "won": true,
      "result": "6-2 3-6 6-4"
    },
    {
      "id": "1242217",
      "date": "2026-02-24",
      "tournamentId": 21315,
      "tournamentName": "Dubai Duty Free Tennis Championships - Dubai",
      "opponentId": 14432,
      "opponentName": "Pablo Carreno-Busta",
      "won": false,
      "result": "6-2 6-4"
    },
    {
      "id": "1241813",
      "date": "2026-02-14",
      "tournamentId": 21308,
      "tournamentName": "Dallas Open - Dallas",
      "opponentId": 87562,
      "opponentName": "Ben Shelton",
      "won": false,
      "result": "4-6 6-4 7-6(4)"
    },
    {
      "id": "1241815",
      "date": "2026-02-13",
      "tournamentId": 21308,
      "tournamentName": "Dallas Open - Dallas",
      "opponentId": 36519,
      "opponentName": "Alejandro Davidovich Fokina",
      "won": true,
      "result": "5-7 6-4 6-3"
    },
    {
      "id": "1241816",
      "date": "2026-02-12",
      "tournamentId": 21308,
      "tournamentName": "Dallas Open - Dallas",
      "opponentId": 39152,
      "opponentName": "Aleksandar Kovacevic",
      "won": true,
      "result": "6-4 6-4"
    },
    {
      "id": "1241844",
      "date": "2026-02-10",
      "tournamentId": 21308,
      "tournamentName": "Dallas Open - Dallas",
      "opponentId": 99691,
      "opponentName": "Rafael Jodar",
      "won": true,
      "result": "6-1 6-2"
    },
    {
      "id": "1241469",
      "date": "2026-01-22",
      "tournamentId": 21305,
      "tournamentName": "Australian Open - Melbourne",
      "opponentId": 6101,
      "opponentName": "Marin Cilic",
      "won": false,
      "result": "6-4 6-3 6-2"
    }
  ],
  "Grass": [
    {
      "id": "118036124",
      "date": "2026-06-08",
      "tournamentId": 21331,
      "tournamentName": "Libema Open - 's-Hertogenbosch",
      "opponentId": 6101,
      "opponentName": "Marin Cilic",
      "won": false,
      "result": "6-7(5) 6-4 7-5"
    },
    {
      "id": "1172551",
      "date": "2025-07-01",
      "tournamentId": 20348,
      "tournamentName": "Wimbledon - London",
      "opponentId": 66828,
      "opponentName": "Mariano Navone",
      "won": false,
      "result": "3-6 6-4 6-1 6-4"
    },
    {
      "id": "1172252",
      "date": "2025-06-19",
      "tournamentId": 20344,
      "tournamentName": "Terra Wortmann Open - Halle",
      "opponentId": 67546,
      "opponentName": "Flavio Cobolli",
      "won": false,
      "result": "7-6(2) 4-6 7-6(5)"
    },
    {
      "id": "1172257",
      "date": "2025-06-17",
      "tournamentId": 20344,
      "tournamentName": "Terra Wortmann Open - Halle",
      "opponentId": 38911,
      "opponentName": "Ugo Humbert",
      "won": true,
      "result": "6-4 4-6 7-6(4)"
    },
    {
      "id": "1172196",
      "date": "2025-06-10",
      "tournamentId": 20343,
      "tournamentName": "Boss Open - Stuttgart",
      "opponentId": 28170,
      "opponentName": "Arthur Rinderknech",
      "won": false,
      "result": "6-4 2-6 6-0"
    },
    {
      "id": "1103474",
      "date": "2024-07-06",
      "tournamentId": 19391,
      "tournamentName": "Wimbledon - London",
      "opponentId": 87562,
      "opponentName": "Ben Shelton",
      "won": false,
      "result": "6-7(4) 6-2 6-4 4-6 6-2"
    },
    {
      "id": "1103456",
      "date": "2024-07-04",
      "tournamentId": 19391,
      "tournamentName": "Wimbledon - London",
      "opponentId": 29732,
      "opponentName": "Daniel Altmaier",
      "won": true,
      "result": "7-6(3) 6-3 1-6 6-7(3) 6-4"
    },
    {
      "id": "1103436",
      "date": "2024-07-01",
      "tournamentId": 19391,
      "tournamentName": "Wimbledon - London",
      "opponentId": 27482,
      "opponentName": "Nicolas Jarry",
      "won": true,
      "result": "6-1 7-5 6-4"
    },
    {
      "id": "1103093",
      "date": "2024-06-13",
      "tournamentId": 19386,
      "tournamentName": "Boss Open - Stuttgart",
      "opponentId": 29812,
      "opponentName": "Matteo Berrettini",
      "won": false,
      "result": "6-4 6-4"
    },
    {
      "id": "1103095",
      "date": "2024-06-11",
      "tournamentId": 19386,
      "tournamentName": "Boss Open - Stuttgart",
      "opponentId": 35323,
      "opponentName": "Matteo Martineau",
      "won": true,
      "result": "7-6(5) 7-5"
    }
  ],
  "updatedAt": 1781321450281,
  "playerName": "Denis Shapovalov"
}