{
  "Clay": [
    {
      "id": "863548",
      "date": "2020-11-22",
      "tournamentId": 16857,
      "tournamentName": "Lima Challenger",
      "opponentId": 28904,
      "opponentName": "Vitaliy Sachko",
      "won": false,
      "result": "4-0 ret."
    },
    {
      "id": "734308",
      "date": "2018-03-31",
      "tournamentId": 14917,
      "tournamentName": "Panama City Challenger",
      "opponentId": 34968,
      "opponentName": "Nicolas Mejia",
      "won": false,
      "result": "7-5 6-1"
    }
  ],
  "Hard": [],
  "Grass": [],
  "updatedAt": 1782512118420,
  "playerName": "Sergio Galdos"
}