{
  "Clay": [
    {
      "id": "1021861",
      "date": "2023-05-01",
      "tournamentId": 18752,
      "tournamentName": "M25 Santa Margherita di Pula 5",
      "opponentId": 74880,
      "opponentName": "Stefanos Sakellaridis",
      "won": false,
      "result": "2-6 6-2 7-6(2)"
    },
    {
      "id": "1004726",
      "date": "2023-04-10",
      "tournamentId": 18702,
      "tournamentName": "M25 Santa Margherita di Pula 2",
      "opponentId": 86070,
      "opponentName": "Leonardo Rossi",
      "won": true,
      "result": "6-4 5-7 10-8"
    },
    {
      "id": "1000429",
      "date": "2023-04-04",
      "tournamentId": 18693,
      "tournamentName": "M25 Santa Margherita di Pula 1",
      "opponentId": 78284,
      "opponentName": "Timo Legout",
      "won": false,
      "result": "6-1 7-5"
    },
    {
      "id": "944364",
      "date": "2022-07-06",
      "tournamentId": 17999,
      "tournamentName": "M25 Marburg 1",
      "opponentId": 23099,
      "opponentName": "Hernan Casanova",
      "won": false,
      "result": "6-2 6-4"
    },
    {
      "id": "909302",
      "date": "2021-12-03",
      "tournamentId": 17492,
      "tournamentName": "M25 Villa Allende 1",
      "opponentId": 77659,
      "opponentName": "Juan Bautista Torres",
      "won": false,
      "result": "6-0 6-1"
    }
  ],
  "Hard": [
    {
      "id": "926091",
      "date": "2022-04-01",
      "tournamentId": 17727,
      "tournamentName": "M15 Monastir 12",
      "opponentId": 66878,
      "opponentName": "Khololwam Montsi",
      "won": false,
      "result": "6-3 7-6(4)"
    },
    {
      "id": "924245",
      "date": "2022-03-16",
      "tournamentId": 17707,
      "tournamentName": "M15 Monastir 10",
      "opponentId": 61667,
      "opponentName": "Bu Yunchaokete",
      "won": false,
      "result": "6-1 6-0"
    },
    {
      "id": "918021",
      "date": "2022-02-04",
      "tournamentId": 17625,
      "tournamentName": "M25 Campos do Jordao 1",
      "opponentId": 69729,
      "opponentName": "Pedro Boscardin Dias",
      "won": false,
      "result": "6-7(4) 6-4 10-4"
    },
    {
      "id": "903485",
      "date": "2021-10-23",
      "tournamentId": 17415,
      "tournamentName": "M15 Monastir 40",
      "opponentId": 50146,
      "opponentName": "Moerani Bouzige",
      "won": false,
      "result": "6-2 6-1"
    },
    {
      "id": "901541",
      "date": "2021-10-08",
      "tournamentId": 17391,
      "tournamentName": "M15 Monastir 38",
      "opponentId": 44595,
      "opponentName": "Ugo Blanchet",
      "won": false,
      "result": "7-5 6-3"
    },
    {
      "id": "892828",
      "date": "2021-08-09",
      "tournamentId": 17264,
      "tournamentName": "M15 Monastir 30",
      "opponentId": 62046,
      "opponentName": "Taisei Ichikawa",
      "won": false,
      "result": "6-1 6-2"
    },
    {
      "id": "892087",
      "date": "2021-08-01",
      "tournamentId": 17254,
      "tournamentName": "M15 Monastir 29",
      "opponentId": 67424,
      "opponentName": "Alec Deckers",
      "won": true,
      "result": "6-7(4) 7-5 10-7"
    },
    {
      "id": "799411",
      "date": "2019-02-25",
      "tournamentId": 15784,
      "tournamentName": "M15 Faro 1",
      "opponentId": 48228,
      "opponentName": "Lorenzo Bocchi",
      "won": true,
      "result": "6-3 7-6(4)"
    }
  ],
  "Grass": [],
  "updatedAt": 1781001774281,
  "playerName": "Mateo Nicolas Martinez"
}