{
  "player1Stats": {
    "player1Id": 41083,
    "aces": 4,
    "doubleFaults": 5,
    "firstServe": 51,
    "firstServeOf": 109,
    "winningOnFirstServe": 32,
    "winningOnFirstServeOf": 51,
    "winningOnSecondServe": 31,
    "winningOnSecondServeOf": 58,
    "breakPointFacedGm": 13,
    "breakPointSavedGm": 8,
    "breakPointChanceGm": 16,
    "breakPointWonGm": 8,
    "winners": null,
    "unforcedErrors": null,
    "netApproaches": null,
    "netApproachesOf": null,
    "totalPointsWon": 117,
    "fastestServe": null,
    "averageFirstServeSpeed": null,
    "averageSecondServeSpeed": null
  },
  "player2Stats": {
    "player2Id": 50133,
    "aces": 2,
    "doubleFaults": 6,
    "firstServe": 64,
    "firstServeOf": 107,
    "winningOnFirstServe": 35,
    "winningOnFirstServeOf": 64,
    "winningOnSecondServe": 18,
    "winningOnSecondServeOf": 43,
    "breakPointFacedGm": 16,
    "breakPointSavedGm": 8,
    "breakPointChanceGm": 13,
    "breakPointWonGm": 5,
    "winners": null,
    "unforcedErrors": null,
    "netApproaches": null,
    "netApproachesOf": null,
    "totalPointsWon": 99,
    "fastestServe": null,
    "averageFirstServeSpeed": null,
    "averageSecondServeSpeed": null
  }
}