{
  "eventId": 13699893,
  "homeId": 200159,
  "awayId": 334289,
  "home": {
    "firstServeOf": 74,
    "firstServe": 52,
    "winningOnFirstServe": 35,
    "winningOnSecondServe": 10,
    "aces": 3,
    "doubleFaults": 4,
    "breakPointsFaced": 7,
    "breakPointsSaved": 4
  },
  "away": {
    "firstServeOf": 93,
    "firstServe": 56,
    "winningOnFirstServe": 39,
    "winningOnSecondServe": 12,
    "aces": 14,
    "doubleFaults": 7,
    "breakPointsFaced": 14,
    "breakPointsSaved": 11
  }
}