{
  "player1Stats": {
    "player1Id": 83555,
    "aces": 0,
    "doubleFaults": 1,
    "firstServe": 36,
    "firstServeOf": 46,
    "winningOnFirstServe": 20,
    "winningOnFirstServeOf": 36,
    "winningOnSecondServe": 7,
    "winningOnSecondServeOf": 10,
    "breakPointFacedGm": 3,
    "breakPointSavedGm": 1,
    "breakPointChanceGm": 11,
    "breakPointWonGm": 7,
    "winners": null,
    "unforcedErrors": null,
    "netApproaches": null,
    "netApproachesOf": null,
    "totalPointsWon": 58,
    "fastestServe": null,
    "averageFirstServeSpeed": null,
    "averageSecondServeSpeed": null
  },
  "player2Stats": {
    "player2Id": 101054,
    "aces": 0,
    "doubleFaults": 1,
    "firstServe": 20,
    "firstServeOf": 44,
    "winningOnFirstServe": 7,
    "winningOnFirstServeOf": 20,
    "winningOnSecondServe": 6,
    "winningOnSecondServeOf": 24,
    "breakPointFacedGm": 11,
    "breakPointSavedGm": 4,
    "breakPointChanceGm": 3,
    "breakPointWonGm": 2,
    "winners": null,
    "unforcedErrors": null,
    "netApproaches": null,
    "netApproachesOf": null,
    "totalPointsWon": 32,
    "fastestServe": null,
    "averageFirstServeSpeed": null,
    "averageSecondServeSpeed": null
  }
}