{
  "eventId": 16287118,
  "homeId": 124930,
  "awayId": 187236,
  "home": {
    "firstServeOf": 105,
    "firstServe": 71,
    "winningOnFirstServe": 56,
    "winningOnSecondServe": 18,
    "aces": 11,
    "doubleFaults": 1,
    "breakPointsFaced": 3,
    "breakPointsSaved": 2
  },
  "away": {
    "firstServeOf": 94,
    "firstServe": 60,
    "winningOnFirstServe": 54,
    "winningOnSecondServe": 18,
    "aces": 15,
    "doubleFaults": 5,
    "breakPointsFaced": 1,
    "breakPointsSaved": 0
  }
}