{
  "eventId": 15757459,
  "homeId": 280151,
  "awayId": 194186,
  "home": {
    "firstServeOf": 73,
    "firstServe": 49,
    "winningOnFirstServe": 41,
    "winningOnSecondServe": 11,
    "aces": 11,
    "doubleFaults": 5,
    "breakPointsFaced": 4,
    "breakPointsSaved": 4
  },
  "away": {
    "firstServeOf": 57,
    "firstServe": 34,
    "winningOnFirstServe": 26,
    "winningOnSecondServe": 12,
    "aces": 3,
    "doubleFaults": 0,
    "breakPointsFaced": 2,
    "breakPointsSaved": 0
  }
}