{
  "eventId": 16465453,
  "homeId": 106755,
  "awayId": 93597,
  "home": {
    "firstServeOf": 99,
    "firstServe": 66,
    "winningOnFirstServe": 53,
    "winningOnSecondServe": 23,
    "aces": 18,
    "doubleFaults": 4,
    "breakPointsFaced": 0,
    "breakPointsSaved": 0
  },
  "away": {
    "firstServeOf": 123,
    "firstServe": 77,
    "winningOnFirstServe": 56,
    "winningOnSecondServe": 25,
    "aces": 10,
    "doubleFaults": 4,
    "breakPointsFaced": 7,
    "breakPointsSaved": 6
  }
}